fsm.v

module fsm
(
    input clk,		// State updates and output transitions are synchronous
    input negativeedge_sclk,
    input positiveedge_sclk,
    input cs,
    input mosi,
    output reg MISO_BUF,
    output reg ADDR_WE,
    output reg DM_WE,
    output reg SR_WE
);

    // State encoding (one-hot)
    reg [4:0] state;
    localparam  IDLE = 5'd0,
		ACTIVE = 5'd1,
    FIND_ADDR0 = 5'd2,
    FIND_ADDR1 = 5'd3,
    FIND_ADDR2 = 5'd4,
    FIND_ADDR3 = 5'd5,
    FIND_ADDR4 = 5'd6,
    FIND_ADDR5 = 5'd7,
    FIND_ADDR6 = 5'd8,

    READ_STATE = 5'd9,
    DM_LOAD_TO_SR = 5'd10,
    DISEN_SR_WE = 5'd11,
    READ0 = 5'd12,
    READ1 = 5'd13,
    READ2 = 5'd14,
    READ3 = 5'd15,
    READ4 = 5'd16,
    READ5 = 5'd17,
    READ6 = 5'd18,
    READ7 = 5'd19,

    WRITE_STATE = 5'd20,
    LOAD_RW = 5'd21,
    WRITE0 = 5'd22,
    WRITE1 = 5'd23,
    WRITE2 = 5'd24,
    WRITE3 = 5'd25,
    WRITE4 = 5'd26,
    WRITE5 = 5'd27,
    WRITE6 = 5'd28,
    WRITE7 = 5'd29;


    // State update logic
    always @(posedge clk) begin
        // Begin in OFF state out of reset (synchronous reset)
        if (cs) begin
            state <= IDLE;
        end

        else begin
            case (state)
                IDLE: begin
                    if (cs==0)
                        state <= ACTIVE;
                    else
                        state <= IDLE;
                end

                ACTIVE: begin
                    if (positiveedge_sclk)
                        state <= FIND_ADDR0;
                    else
                        state <= ACTIVE;
                end

                FIND_ADDR0: begin
                    if (positiveedge_sclk)
                        state <= FIND_ADDR1;
                    else
                        state <= FIND_ADDR0;
                end

                FIND_ADDR1: begin
                    if (positiveedge_sclk)
                        state <= FIND_ADDR2;
                    else
                        state <= FIND_ADDR1;
                end

                FIND_ADDR2: begin
                    if (positiveedge_sclk)
                        state <= FIND_ADDR3;
                    else
                        state <= FIND_ADDR2;
                end

                FIND_ADDR3: begin
                    if (positiveedge_sclk)
                        state <= FIND_ADDR4;
                    else
                        state <= FIND_ADDR3;
                end

                FIND_ADDR4: begin
                    if (positiveedge_sclk)
                        state <= FIND_ADDR5;
                    else
                        state <= FIND_ADDR4;
                end

                FIND_ADDR5: begin
                    if (positiveedge_sclk)
                        state <= FIND_ADDR6;
                    else
                        state <= FIND_ADDR5;
                end

                FIND_ADDR6: begin
                    if (negativeedge_sclk == 1 && mosi == 1)
                        state <= READ_STATE;
                    else if (negativeedge_sclk == 1 && mosi == 0)
                        state <= WRITE_STATE;
                    else
                        state <= FIND_ADDR6;
                end

                READ_STATE: begin
                    if (positiveedge_sclk)
                        state <= DM_LOAD_TO_SR;
                    else
                        state <= READ_STATE;
                end

                DM_LOAD_TO_SR: begin
                    if (negativeedge_sclk)
                        state <= DISEN_SR_WE;
                    else
                        state <= DM_LOAD_TO_SR;
                end

                DISEN_SR_WE: begin
                    if (positiveedge_sclk)
                        state <= READ0;
                    else
                        state <= DISEN_SR_WE;
                end

                READ0: begin
                    if (positiveedge_sclk)
                        state <= READ1;
                    else
                        state <= READ0;
                end

                READ1: begin
                    if (positiveedge_sclk)
                        state <= READ2;
                    else
                        state <= READ1;
                end

                READ2: begin
                    if (positiveedge_sclk)
                        state <= READ3;
                    else
                        state <= READ2;
                end

                READ3: begin
                    if (positiveedge_sclk)
                        state <= READ4;
                    else
                        state <= READ3;
                end

                READ4: begin
                    if (positiveedge_sclk)
                        state <= READ5;
                    else
                        state <= READ4;
                end

                READ5: begin
                    if (positiveedge_sclk)
                        state <= READ6;
                    else
                        state <= READ5;
                end

                READ6: begin
                    if (positiveedge_sclk)
                        state <= READ7;
                    else
                        state <= READ6;
                end

                READ7: begin
                    if (positiveedge_sclk)
                        state <= FIND_ADDR0;
                    else
                        state <= READ7;
                end

                WRITE_STATE: begin
                    if (positiveedge_sclk)
                        state <= LOAD_RW;
                    else
                        state <= WRITE_STATE;
                end

                LOAD_RW: begin
                    if (positiveedge_sclk)
                        state <= WRITE0;
                    else
                        state <= LOAD_RW;
                end

                WRITE0: begin
                    if (positiveedge_sclk)
                        state <= WRITE1;
                    else
                        state <= WRITE0;
                end

                WRITE1: begin
                    if (positiveedge_sclk)
                        state <= WRITE2;
                    else
                        state <= WRITE1;
                end

                WRITE2: begin
                    if (positiveedge_sclk)
                        state <= WRITE3;
                    else
                        state <= WRITE2;
                end

                WRITE3: begin
                    if (positiveedge_sclk)
                        state <= WRITE4;
                    else
                        state <= WRITE3;
                end

                WRITE4: begin
                    if (positiveedge_sclk)
                        state <= WRITE5;
                    else
                        state <= WRITE4;
                end

                WRITE5: begin
                    if (positiveedge_sclk)
                        state <= WRITE6;
                    else
                        state <= WRITE5;
                end

                WRITE6: begin
                    if (positiveedge_sclk)
                        state <= WRITE7;
                    else
                        state <= WRITE6;
                end

                WRITE7: begin
                    if (positiveedge_sclk)
                        state <= FIND_ADDR0;
                    else
                        state <= WRITE7;
                end

            endcase
        end

    end	// @(posedge clk)


    // Output logic (depends only on state - Moore machine)
    always @(state) begin
        case (state)
            IDLE: begin
                MISO_BUF = 0;
                ADDR_WE = 0;
                DM_WE = 0;
                SR_WE = 0; end
            ACTIVE: begin
                MISO_BUF = 1;
                ADDR_WE = 0;
                DM_WE = 0;
                SR_WE = 0; end
            FIND_ADDR0: begin
                MISO_BUF = 1;
                ADDR_WE = 0;
                DM_WE = 0;
                SR_WE = 0; end
            FIND_ADDR1: begin
                MISO_BUF = 1;
                ADDR_WE = 0;
                DM_WE = 0;
                SR_WE = 0; end
            FIND_ADDR2: begin
                MISO_BUF = 1;
                ADDR_WE = 0;
                DM_WE = 0;
                SR_WE = 0; end
            FIND_ADDR3: begin
                MISO_BUF = 1;
                ADDR_WE = 0;
                DM_WE = 0;
                SR_WE = 0; end
            FIND_ADDR4: begin
                MISO_BUF = 1;
                ADDR_WE = 0;
                DM_WE = 0;
                SR_WE = 0; end
            FIND_ADDR5: begin
                MISO_BUF = 1;
                ADDR_WE = 0;
                DM_WE = 0;
                SR_WE = 0; end
            FIND_ADDR6: begin
                MISO_BUF = 1;
                ADDR_WE = 1;
                DM_WE = 0;
                SR_WE = 0; end

            READ_STATE: begin
                MISO_BUF = 1;
                ADDR_WE = 0;
                DM_WE = 0;
                SR_WE = 1; end
            DM_LOAD_TO_SR: begin
                MISO_BUF = 1;
                ADDR_WE = 0;
                DM_WE = 0;
                SR_WE = 0; end
            DISEN_SR_WE: begin
                MISO_BUF = 1;
                ADDR_WE = 0;
                DM_WE = 0;
                SR_WE = 0; end

            READ0: begin
                MISO_BUF = 1;
                ADDR_WE = 0;
                DM_WE = 0;
                SR_WE = 0; end
            READ1: begin
                MISO_BUF = 1;
                ADDR_WE = 0;
                DM_WE = 0;
                SR_WE = 0; end
            READ2: begin
                MISO_BUF = 1;
                ADDR_WE = 0;
                DM_WE = 0;
                SR_WE = 0; end
            READ3: begin
                MISO_BUF = 1;
                ADDR_WE = 0;
                DM_WE = 0;
                SR_WE = 0; end
            READ4: begin
                MISO_BUF = 1;
                ADDR_WE = 0;
                DM_WE = 0;
                SR_WE = 0; end
            READ5: begin
                MISO_BUF = 1;
                ADDR_WE = 0;
                DM_WE = 0;
                SR_WE = 0; end
            READ6: begin
                MISO_BUF = 1;
                ADDR_WE = 0;
                DM_WE = 0;
                SR_WE = 0; end
            READ7: begin
                MISO_BUF = 1;
                ADDR_WE = 0;
                DM_WE = 0;
                SR_WE = 0; end

            WRITE_STATE: begin
                MISO_BUF = 1;
                ADDR_WE = 0;
                DM_WE = 0;
                SR_WE = 0; end
            LOAD_RW: begin
                MISO_BUF = 1;
                ADDR_WE = 0;
                DM_WE = 0;
                SR_WE = 0; end

            WRITE0: begin
                MISO_BUF = 1;
                ADDR_WE = 0;
                DM_WE = 0;
                SR_WE = 0; end
            WRITE1: begin
                MISO_BUF = 1;
                ADDR_WE = 0;
                DM_WE = 0;
                SR_WE = 0; end
            WRITE2: begin
                MISO_BUF = 1;
                ADDR_WE = 0;
                DM_WE = 0;
                SR_WE = 0; end
            WRITE3: begin
                MISO_BUF = 1;
                ADDR_WE = 0;
                DM_WE = 0;
                SR_WE = 0; end
            WRITE4: begin
                MISO_BUF = 1;
                ADDR_WE = 0;
                DM_WE = 0;
                SR_WE = 0; end
            WRITE5: begin
                MISO_BUF = 1;
                ADDR_WE = 0;
                DM_WE = 0;
                SR_WE = 0; end
            WRITE6: begin
                MISO_BUF = 1;
                ADDR_WE = 0;
                DM_WE = 0;
                SR_WE = 0; end
            WRITE7: begin
                MISO_BUF = 1;
                ADDR_WE = 0;
                DM_WE = 1;
                SR_WE = 0; end
        endcase
    end


endmodule

fsm_bench.t.v
// Testbench for thermostat FSM example

`timescale 1ns / 1ps

`include "fsm.v"

module fsm_test ();
    reg clk, negativeedge_sclk, positiveedge_sclk, cs, mosi;	// FSM inputs
    wire MISO_BUF, ADDR_WE, DM_WE, SR_WE;	// FSM output

    // Instantiate DUT
    fsm dut(.clk(clk), .negativeedge_sclk(negativeedge_sclk),
                   .positiveedge_sclk(positiveedge_sclk), .cs(cs),
                   .mosi(mosi), .MISO_BUF(MISO_BUF), .ADDR_WE(ADDR_WE), .DM_WE(DM_WE), .SR_WE(SR_WE));
    // Create clock signal
    initial clk=0;
    always #10 clk =! clk;


   // Test sequence
   initial begin
       $dumpfile("fsm.vcd");
       $dumpvars(0, dut);

        //testing idle state
       negativeedge_sclk = 0; positiveedge_sclk = 0; cs = 1; mosi = 0; #35
      if(MISO_BUF != 0 || DM_WE != 0 || ADDR_WE != 0 || SR_WE != 0) begin
        $display("error in test #1" );
        $display("MISO_BUF | Expected: 0 Got: %d", MISO_BUF);
        $display("DM_WE | Expected: 0 Got: %d", DM_WE);
        $display("ADDR_WE | Expected: 0 Got: %d", ADDR_WE);
        $display("ADDR_WE | Expected: 0 Got: %d", SR_WE);
      end
      else begin
        $display("Passed Test 1 : Idle");
        end
      //testing active state
      negativeedge_sclk = 0; positiveedge_sclk = 0; cs = 0; mosi = 0; #35

     if(MISO_BUF != 1 || DM_WE != 0 || ADDR_WE != 0 || SR_WE != 0) begin
       $display("error in test #2" );
       $display("MISO_BUF | Expected: 1 Got: %d", MISO_BUF);
       $display("DM_WE | Expected: 0 Got: %d", DM_WE);
       $display("ADDR_WE | Expected: 0 Got: %d", ADDR_WE);
       $display("SR_WE | Expected: 0 Got: %d", SR_WE);
     end
     else begin
       $display("Passed Test 2 : Active");
       end

       //testing Finding address
       negativeedge_sclk = 0; positiveedge_sclk = 1; cs = 0; mosi = 1; #11
    if(MISO_BUF != 1 || DM_WE != 0 || ADDR_WE != 0 || SR_WE != 0) begin
         $display("error in test #3" );
         $display("MISO_BUF | Expected: 1 Got: %d", MISO_BUF);
         $display("DM_WE | Expected: 0 Got: %d", DM_WE);
         $display("ADDR_WE | Expected: 0 Got: %d", ADDR_WE);
         $display("SR_WE | Expected: 0 Got: %d", SR_WE);
       end
       else begin
         $display("Passed Test 3 : Address[0] Found");
         end
      #100
      //Determining Write o
      mosi = 0; #4
      positiveedge_sclk = 1; cs = 0; #6
      negativeedge_sclk = 1;positiveedge_sclk = 0; #1

      if(MISO_BUF != 1 || DM_WE != 0 || ADDR_WE != 1 || SR_WE != 0) begin
           $display("error in test #4" );
           $display("MISO_BUF | Expected: 1 Got: %d", MISO_BUF);
           $display("DM_WE | Expected: 0 Got: %d", DM_WE);
           $display("ADDR_WE | Expected: 1 Got: %d", ADDR_WE);
           $display("SR_WE | Expected: 0 Got: %d", SR_WE);
         end
         else begin
           $display("Passed Test 4 : Determining Write State");
           end
        #30
       positiveedge_sclk = 1; cs = 0; negativeedge_sclk = 0; #180


       if(MISO_BUF != 1 || DM_WE != 1 || ADDR_WE != 0 || SR_WE != 0) begin
            $display("error in test #5" );
            $display("MISO_BUF | Expected: 1 Got: %d", MISO_BUF);
            $display("DM_WE | Expected: 1 Got: %d", DM_WE);
            $display("ADDR_WE | Expected: 0 Got: %d", ADDR_WE);
            $display("SR_WE | Expected: 0 Got: %d", SR_WE);
          end
          else begin
            $display("Passed Test 5 : Sending to Data Memory");
            end



            //Determining read o
            mosi = 1; #4
            positiveedge_sclk = 1; cs = 0; #6
            positiveedge_sclk = 0;  #1

        if(MISO_BUF != 1 || DM_WE != 0 || ADDR_WE != 1 || SR_WE != 0) begin
             $display("error in test #6" );
             $display("MISO_BUF | Expected: 1 Got: %d", MISO_BUF);
             $display("DM_WE | Expected: 0 Got: %d", DM_WE);
             $display("ADDR_WE | Expected: 1 Got: %d", ADDR_WE);
             $display("SR_WE | Expected: 0 Got: %d", SR_WE);
           end
           else begin
             $display("Passed Test 6 : Determining read State");
             end


     #1000
     $dumpflush;
     $finish;		// End simulation (otherwise clk is infinite)
   end


endmodule

fsm.vcd
$date
	Mon Oct 15 21:58:10 2018
$end
$version
	Icarus Verilog
$end
$timescale
	1ps
$end
$scope module fsm_test $end
$scope module dut $end
$var wire 1 ! clk $end
$var wire 1 " cs $end
$var wire 1 # mosi $end
$var wire 1 $ negativeedge_sclk $end
$var wire 1 % positiveedge_sclk $end
$var reg 1 & ADDR_WE $end
$var reg 1 ' DM_WE $end
$var reg 1 ( MISO_BUF $end
$var reg 1 ) SR_WE $end
$var reg 5 * state [4:0] $end
$upscope $end
$upscope $end
$enddefinitions $end
#0
$dumpvars
bx *
x)
x(
x'
x&
0%
0$
0#
1"
0!
$end
#10000
0)
0'
0&
0(
b0 *
1!
#20000
0!
#30000
1!
#35000
0"
#40000
0!
#50000
1(
b1 *
1!
#60000
0!
#70000
b10 *
1!
1#
1%
#80000
0!
#90000
b11 *
1!
#100000
0!
#110000
b100 *
1!
#120000
0!
#130000
b101 *
1!
#140000
0!
#150000
b110 *
1!
#160000
0!
#170000
b111 *
1!
#180000
0!
#181000
0#
#190000
1&
b1000 *
1!
#191000
0%
1$
#200000
0!
#210000
0&
b10100 *
1!
#220000
0!
#222000
0$
1%
#230000
b10101 *
1!
#240000
0!
#250000
b10110 *
1!
#260000
0!
#270000
b10111 *
1!
#280000
0!
#290000
b11000 *
1!
#300000
0!
#310000
b11001 *
1!
#320000
0!
#330000
b11010 *
1!
#340000
0!
#350000
b11011 *
1!
#360000
0!
#370000
b11100 *
1!
#380000
0!
#390000
1'
b11101 *
1!
#400000
0!
#402000
1#
#410000
0'
b10 *
1!
#412000
1$
#420000
0!
#430000
b11 *
1!
#440000
0!
#450000
b100 *
1!
#460000
0!
#470000
b101 *
1!
#480000
0!
#490000
b110 *
1!
#500000
0!
#510000
b111 *
1!
#520000
0!
#530000
1&
b1000 *
1!
#540000
0!
#550000
1)
0&
b1001 *
1!
#560000
0!
#570000
0)
b1010 *
1!
#580000
0!
#590000
b1011 *
1!
#600000
0!
#610000
b1100 *
1!
#620000
0!
#630000
b1101 *
1!
#640000
0!
#650000
b1110 *
1!
#660000
0!
#670000
b1111 *
1!
#680000
0!
#690000
b10000 *
1!
#700000
0!
#710000
b10001 *
1!
#720000
0!
#730000
b10010 *
1!
#740000
0!
#750000
b10011 *
1!
#760000
0!
#770000
b10 *
1!
#780000
0!
#790000
b11 *
1!
#800000
0!
#810000
b100 *
1!
#820000
0!
#830000
b101 *
1!
#840000
0!
#850000
b110 *
1!
#860000
0!
#870000
b111 *
1!
#880000
0!
#890000
1&
b1000 *
1!
#900000
0!
#910000
1)
0&
b1001 *
1!
#920000
0!
#930000
0)
b1010 *
1!
#940000
0!
#950000
b1011 *
1!
#960000
0!
#970000
b1100 *
1!
#980000
0!
#990000
b1101 *
1!
#1000000
0!
#1010000
b1110 *
1!
#1020000
0!
#1030000
b1111 *
1!
#1040000
0!
#1050000
b10000 *
1!
#1060000
0!
#1070000
b10001 *
1!
#1080000
0!
#1090000
b10010 *
1!
#1100000
0!
#1110000
b10011 *
1!
#1120000
0!
#1130000
b10 *
1!
#1140000
0!
#1150000
b11 *
1!
#1160000
0!
#1170000
b100 *
1!
#1180000
0!
#1190000
b101 *
1!
#1200000
0!
#1210000
b110 *
1!
#1220000
0!
#1230000
b111 *
1!
#1240000
0!
#1250000
1&
b1000 *
1!
#1260000
0!
#1270000
1)
0&
b1001 *
1!
#1280000
0!
#1290000
0)
b1010 *
1!
#1300000
0!
#1310000
b1011 *
1!
#1320000
0!
#1330000
b1100 *
1!
#1340000
0!
#1350000
b1101 *
1!
#1360000
0!
#1370000
b1110 *
1!
#1380000
0!
#1390000
b1111 *
1!
#1400000
0!
#1410000
b10000 *
1!
