inputconditioner.v
//------------------------------------------------------------------------
// Input Conditioner
//    1) Synchronizes input to clock domain
//    2) Debounces input
//    3) Creates pulses at edge transitions
//------------------------------------------------------------------------
`define NAND nand #20
`define NOT not #10
`timescale 1 ns / 1 ps

module inputconditioner
(
input 	    clk,            // Clock domain to synchronize input to
input	    noisysignal,    // (Potentially) noisy input signal
output reg  conditioned,    // Conditioned output signal
output reg  positiveedge,   // 1 clk pulse at rising edge of conditioned
output reg  negativeedge    // 1 clk pulse at falling edge of conditioned
);

    parameter counterwidth = 3; // Counter size, in bits, >= log2(waittime)
    parameter waittime = 3;     // Debounce delay, in clock cycles

    reg[counterwidth-1:0] counter = 0;
    reg synchronizer0 = 0;
    reg synchronizer1 = 0;
    reg posedgecounter = 0;
    reg negedgecounter = 0;

    always @(posedge clk ) begin
        if(posedgecounter > 0) begin
          positiveedge <= 0;
          posedgecounter <= 0;
        end

        if(negedgecounter > 0) begin
          negativeedge <= 0;
          negedgecounter <= 0;
        end

        if(conditioned == synchronizer1)
            counter <= 0;
        else begin
            if( counter == waittime) begin
                counter <= 0;
                conditioned <= synchronizer1;

            if( conditioned < synchronizer0) begin
                positiveedge <= 1;
                posedgecounter <= posedgecounter + 1; end

            if( conditioned > synchronizer0) begin
                negativeedge <= 1;
                negedgecounter <= negedgecounter + 1; end end

                counter <= counter+1;
        end
        synchronizer0 <= noisysignal;
        synchronizer1 <= synchronizer0;
    end

endmodule

// module gated_d_latch(
//    input data,
//    input clk,
//    output q
//    );
//
//    wire notQ;
//    wire wire0;
//    wire wire1;
// //
//    `NAND nand1(wire0, data, clk);
//    `NAND nand2(wire1, wire0, clk);
//    `NAND nand3(q,wire0, notQ);
//    `NAND nand4(notQ, wire1, q);
//  endmodule

inputconditioner.t.v
//------------------------------------------------------------------------
// Input Conditioner test bench
//------------------------------------------------------------------------
`include "inputconditioner.v"
module testConditioner();
    reg clk;
    reg pin;
    wire conditioned;
    wire rising;
    wire falling;
    inputconditioner dut(.clk(clk),
			 .noisysignal(pin),
		 	.conditioned(conditioned),
			 .positiveedge(rising),
			 .negativeedge(falling));


    // Generate clock (50MHz)
    initial clk=0;
    always #10 clk=!clk;    // 50MHz Clock

    initial begin
        $dumpfile("inputconditioner.vcd");
    	$dumpvars(0, dut);
	
	pin = 0; #100
	pin = 1; #50
	pin = 1; #50
	pin = 1; #50
	pin = 1; #50
	pin = 1; #50
	pin = 1; #50 // clean high
	pin = 0; #50
	pin = 0; #50
	pin = 0; #50
	pin = 0; #50
	pin = 0; #50 //clean low 
	pin = 1; #10 // bounceing high
	pin = 0; #10
	pin = 1; #10
	pin = 1; #50
	pin = 1; #50
	pin = 1; #50
	pin = 1; #50 // bounceing low
	pin = 0; #50
	pin = 0; #50
	pin = 0; #50
	pin = 1; #10 
	pin = 0; #50
	pin = 0; #50
	$dumpflush;
	$finish;
	end
endmodule


//sychronization

//debouncing


//edge detection




//	#200 data_in = 1'b1; 
//	//reset = 1'b1;
//	#200 data_in = 1'b1;
//	//reset = 1'b1;

//	#300 data_in = 1'b1;
//	//reset=1'b0;
//	#600 data_in = 1'b0;
//	#500 data_in = 1'b1;
//	#200 data_in = 1'b0;
//	#400 $stop;

    // Your Test Code
    // Be sure to test each of the three conditioner functions:
    // Synchronization, Debouncing, Edge Detection

inputconditioner.vcd
$date
	Tue Oct  9 10:07:05 2018
$end
$version
	Icarus Verilog
$end
$timescale
	1ps
$end
$scope module testConditioner $end
$scope module dut $end
$var wire 1 ! clk $end
$var wire 1 " noisysignal $end
$var reg 1 # conditioned $end
$var reg 3 $ counter [2:0] $end
$var reg 1 % negativeedge $end
$var reg 1 & negedgecounter $end
$var reg 1 ' posedgecounter $end
$var reg 1 ( positiveedge $end
$var reg 1 ) synchronizer0 $end
$var reg 1 * synchronizer1 $end
$upscope $end
$upscope $end
$enddefinitions $end
#0
$dumpvars
0*
0)
x(
0'
0&
x%
b0 $
x#
0"
0!
$end
#10000
b1 $
1!
#20000
0!
#30000
b10 $
1!
#40000
0!
#50000
b11 $
1!
#60000
0!
#70000
0#
b100 $
1!
#80000
0!
#90000
b0 $
1!
#100000
0!
1"
#110000
1)
1!
#120000
0!
#130000
1*
1!
#140000
0!
#150000
b1 $
1!
#160000
0!
#170000
b10 $
1!
#180000
0!
#190000
b11 $
1!
#200000
0!
#210000
1'
1(
1#
b100 $
1!
#220000
0!
#230000
b0 $
0'
0(
1!
#240000
0!
#250000
1!
#260000
0!
#270000
1!
#280000
0!
#290000
1!
#300000
0!
#310000
1!
#320000
0!
#330000
1!
#340000
0!
#350000
1!
#360000
0!
#370000
1!
#380000
0!
#390000
1!
#400000
0!
0"
#410000
0)
1!
#420000
0!
#430000
0*
1!
#440000
0!
#450000
b1 $
1!
#460000
0!
#470000
b10 $
1!
#480000
0!
#490000
b11 $
1!
#500000
0!
#510000
1&
1%
0#
b100 $
1!
#520000
0!
#530000
b0 $
0&
0%
1!
#540000
0!
#550000
1!
#560000
0!
#570000
1!
#580000
0!
#590000
1!
#600000
0!
#610000
1!
#620000
0!
#630000
1!
#640000
0!
#650000
1)
1!
1"
#660000
0!
0"
#670000
1*
1!
1"
#680000
0!
#690000
b1 $
1!
#700000
0!
#710000
b10 $
1!
#720000
0!
#730000
b11 $
1!
#740000
0!
#750000
1'
1(
1#
b100 $
1!
#760000
0!
#770000
b0 $
0'
0(
1!
#780000
0!
#790000
1!
#800000
0!
#810000
1!
#820000
0!
#830000
1!
#840000
0!
0"
#850000
0)
1!
#860000
0!
#870000
0*
1!
#880000
0!
#890000
b1 $
1!
#900000
0!
#910000
b10 $
1!
#920000
0!
#930000
b11 $
1!
#940000
0!
#950000
1&
1%
0#
b100 $
1!
#960000
0!
#970000
b0 $
0&
0%
1!
#980000
0!
#990000
1)
1!
1"
#1000000
0!
0"
#1010000
1*
0)
1!
#1020000
0!
#1030000
0*
b1 $
1!
#1040000
0!
#1050000
b0 $
1!
