inputconditioner.v
//------------------------------------------------------------------------
// Input Conditioner
//    1) Synchronizes input to clock domain
//    2) Debounces input
//    3) Creates pulses at edge transitions
//------------------------------------------------------------------------
`define NAND nand #20
`define NOT not #10

module inputconditioner
(
input 	    clk,            // Clock domain to synchronize input to
input	    noisysignal,    // (Potentially) noisy input signal
output reg  conditioned,    // Conditioned output signal
output reg  positiveedge,   // 1 clk pulse at rising edge of conditioned
output reg  negativeedge    // 1 clk pulse at falling edge of conditioned
);

    parameter counterwidth = 3; // Counter size, in bits, >= log2(waittime)
    parameter waittime = 3;     // Debounce delay, in clock cycles

    reg[counterwidth-1:0] counter = 0;
    reg synchronizer0 = 0;
    reg synchronizer1 = 0;
/*
    always @(posedge clk ) begin
        if(conditioned == synchronizer1)
            counter <= 0;
        else begin
            if( counter == waittime) begin
                counter <= 0;
                conditioned <= synchronizer1;
                if(conditioned > synchronizer0)
                    positiveedge <= 1
                else if(conditioned < synchronizer0)
                    negativeedge <= 1
                else begin
                positiveedge <= 0
                negativeedge <= 0
                end

            end
            else
                counter <= counter+1;
        end
        synchronizer0 <= noisysignal;
        synchronizer1 <= synchronizer0;
    end
*/
endmodule

module gated_d_latch(
   input data,
   input clk,
   output q
   );

   wire notQ;
   wire wire0;
   wire wire1;
//
   `NAND nand1(wire0, data, clk);
   `NAND nand2(wire1, wire0, clk);
   `NAND nand3(q,wire0, notQ);
   `NAND nand4(notQ, wire1, q);
 endmodule

inputconditioner.t.v
//------------------------------------------------------------------------
// Input Conditioner test bench
//------------------------------------------------------------------------
`include "inputconditioner.v"
module testConditioner();
    reg clk;
    reg pin;
    wire conditioned;
    wire rising;
    wire falling;
    inputconditioner dut(.clk(clk),
			 .noisysignal(pin),
		 	.conditioned(conditioned),
			 .positiveedge(rising),
			 .negativeedge(falling));


    // Generate clock (50MHz)
    initial clk=0;
    always #10 clk=!clk;    // 50MHz Clock

    initial begin
        $dumpfile("inputconditioner.vcd");
    	$dumpvars(0, dut);
	
	pin = 0; #100
	pin = 1; #50
	pin = 1; #50
	pin = 1; #50
	pin = 1; #50
	pin = 1; #50
	pin = 1; #50 // clean high
	pin = 0; #50
	pin = 0; #50
	pin = 0; #50
	pin = 0; #50
	pin = 0; #50 //clean low 
	pin = 1; #10 // bounceing high
	pin = 0; #10
	pin = 1; #10
	pin = 1; #50
	pin = 1; #50
	pin = 1; #50
	pin = 1; #50 // bounceing low
	pin = 0; #50
	pin = 0; #50
	pin = 0; #50
	pin = 1; #10 
	pin = 0; #50
	pin = 0; #50
	$dumpflush;
	$finish;
	end
endmodule


//sychronization

//debouncing


//edge detection




//	#200 data_in = 1'b1; 
//	//reset = 1'b1;
//	#200 data_in = 1'b1;
//	//reset = 1'b1;

//	#300 data_in = 1'b1;
//	//reset=1'b0;
//	#600 data_in = 1'b0;
//	#500 data_in = 1'b1;
//	#200 data_in = 1'b0;
//	#400 $stop;

    // Your Test Code
    // Be sure to test each of the three conditioner functions:
    // Synchronization, Debouncing, Edge Detection

inputconditioner.vcd
$date
	Mon Oct  8 19:06:57 2018
$end
$version
	Icarus Verilog
$end
$timescale
	1s
$end
$scope module testConditioner $end
$scope module dut $end
$var wire 1 ! clk $end
$var wire 1 " noisysignal $end
$var reg 1 # conditioned $end
$var reg 3 $ counter [2:0] $end
$var reg 1 % negativeedge $end
$var reg 1 & positiveedge $end
$var reg 1 ' synchronizer0 $end
$var reg 1 ( synchronizer1 $end
$upscope $end
$upscope $end
$enddefinitions $end
#0
$dumpvars
0(
0'
x&
x%
b0 $
x#
0"
0!
$end
#10
1!
#20
0!
#30
1!
#40
0!
#50
1!
#60
0!
#70
1!
#80
0!
#90
1!
#100
0!
1"
#110
1!
#120
0!
#130
1!
#140
0!
#150
1!
#160
0!
#170
1!
#180
0!
#190
1!
#200
0!
#210
1!
#220
0!
#230
1!
#240
0!
#250
1!
#260
0!
#270
1!
#280
0!
#290
1!
#300
0!
#310
1!
#320
0!
#330
1!
#340
0!
#350
1!
#360
0!
#370
1!
#380
0!
#390
1!
#400
0!
0"
#410
1!
#420
0!
#430
1!
#440
0!
#450
1!
#460
0!
#470
1!
#480
0!
#490
1!
#500
0!
#510
1!
#520
0!
#530
1!
#540
0!
#550
1!
#560
0!
#570
1!
#580
0!
#590
1!
#600
0!
#610
1!
#620
0!
#630
1!
#640
0!
#650
1!
1"
#660
0!
0"
#670
1!
1"
#680
0!
#690
1!
#700
0!
#710
1!
#720
0!
#730
1!
#740
0!
#750
1!
#760
0!
#770
1!
#780
0!
#790
1!
#800
0!
#810
1!
#820
0!
#830
1!
#840
0!
#850
1!
#860
0!
#870
1!
#880
0!
0"
#890
1!
#900
0!
#910
1!
#920
0!
#930
1!
#940
0!
#950
1!
#960
0!
#970
1!
#980
0!
#990
1!
#1000
0!
#1010
1!
#1020
0!
#1030
1!
1"
#1040
0!
0"
