shiftregister.v
//------------------------------------------------------------------------
// Shift Register
//   Parameterized width (in bits)
//   Shift register can operate in two modes:
//      - serial in, parallel out
//      - parallel in, serial out
//------------------------------------------------------------------------

module shiftregister
#(parameter width = 8)
(
input               clk,                // FPGA Clock
input               peripheralClkEdge,  // Edge indicator
input               parallelLoad,       // 1 = Load shift reg with parallelDataIn
input  [width-1:0]  parallelDataIn,     // Load shift reg in parallel
input               serialDataIn,       // Load shift reg serially
output [width-1:0]  parallelDataOut,    // Shift reg data contents
output              serialDataOut       // Positive edge synchronized
);

    reg [width:0]      shiftregistermem;
    always @(posedge clk) begin
        if( parallelLoad == 1)
          // When parallelLoad is asserted, the shift register will take the value of parallelDataIn.
          parallelDataOut <= parallelDataIn;
        else if (peripheralClkEdge == 1) begin
          // When the peripheral clock peripheralClkEdge has an edge, the shift register advances one position:
          // serialDataIn is loaded into the LSB (Least Significant Bit), and the rest of the bits shift up by one.
          shiftregistermem <= {parallelDataIn, serialDataIn};
          parallelDataOut <= shiftregistermem[width-1:0];
        end
        // serialDataOut always presents the Most Significant Bit of the shift register.
        serialDataOut <= parallelDataOut[width-1];
    end
endmodule

shiftregister.t.v
//------------------------------------------------------------------------
// Shift Register test bench
//------------------------------------------------------------------------
`timescale 1 ns / 1 ps
`include "shiftregister.v"
module testshiftregister();

    reg             clk;
    reg             peripheralClkEdge;
    reg             parallelLoad;
    wire[7:0]       parallelDataOut;
    wire            serialDataOut;
    reg[7:0]        parallelDataIn;
    reg             serialDataIn;

    // Instantiate with parameter width = 8
    shiftregister #(8) dut(.clk(clk),
    		           .peripheralClkEdge(peripheralClkEdge),
    		           .parallelLoad(parallelLoad),
    		           .parallelDataIn(parallelDataIn),
    		           .serialDataIn(serialDataIn),
    		           .parallelDataOut(parallelDataOut),
    		           .serialDataOut(serialDataOut));
    // Generate clock (50MHz)
    initial clk=0;
    initial peripheralClkEdge = 0;
    always #10 clk=!clk;    // 50MHz Clock

    always
      begin
      peripheralClkEdge <= 1'b0;
      #9;
      peripheralClkEdge <= 1'b1;
      #2;
      peripheralClkEdge <= 1'b0;
      #9;
      end

    initial begin
    $dumpfile("shifter.vcd");
    $dumpvars(0, dut);


    //Case 1: PIPO
    //Parallel load is always asserted, 8 bits are loaded into place. After these 8 bits are loaded, parallel data in goes to zero, and we observe a full shift in the output.
    parallelDataIn = 8'b11001100;
    parallelLoad= 1;
    #20;
    $display("current register   %b", parallelDataOut);
    parallelDataIn = 8'b0000000;
    #20;
    $display("current register   %b", parallelDataOut);
    parallelDataIn = 8'b1010101;
    #20;
    $display("current register   %b", parallelDataOut);



    //Case 2: SIS0
    //Parallel load is never asserted, we observe a reading of serial data into the LSB
    parallelLoad = 0;
    serialDataIn = 1;
    parallelDataIn = 8'b0110000;
    #20;
    // not working as expected // GTKWAVE does not register serial dataout as getting anything written to it. we should look at shift register.v
    $display("current register LSB   %b", parallelDataOut);
    serialDataIn = 0;
    parallelDataIn = 8'b0010100;
    #20;
    $display("current register LSB   %b", serialDataOut);
    serialDataIn = 1;
    parallelDataIn = 8'b1000101;
    #20;
    $display("current register LSB   %b", serialDataOut);

    //Case 3:
    //Peripheral clock edge is non-periodic, so we observe non-periodic shifting. Parallel load is always asserted.

    //Case 4:
    //Parallel load is toggled.

    parallelDataIn = 8'b11001100; #20
    parallelLoad= 1;
    #5;
    $display("current register   %b", parallelDataOut);
    parallelDataIn = 8'b0000000;
    serialDataIn = 1;
    #27;
    $display("current register   %b", parallelDataOut);
    parallelDataIn = 8'b1010101;
    serialDataIn = 0;
    #20;
    $display("current register   %b", parallelDataOut);

    parallelLoad= 0;
    #35;
    $display("current register   %b", parallelDataOut);
    serialDataIn = 1;
    parallelDataIn = 8'b0000000;
    #27;
    $display("current register   %b", parallelDataOut);
    parallelDataIn = 8'b1010101;
    serialDataIn = 0;
    #20;
    $display("current register   %b", parallelDataOut);
    $dumpflush;
    $finish;
    end

endmodule

shifter.vcd
$date
	Wed Oct 17 10:10:11 2018
$end
$version
	Icarus Verilog
$end
$timescale
	1ps
$end
$scope module testshiftregister $end
$scope module dut $end
$var wire 1 ! clk $end
$var wire 8 " parallelDataIn [7:0] $end
$var wire 1 # parallelLoad $end
$var wire 1 $ peripheralClkEdge $end
$var wire 1 % serialDataIn $end
$var reg 8 & parallelDataOut [7:0] $end
$var reg 1 ' serialDataOut $end
$var reg 8 ( shiftregistermem [7:0] $end
$upscope $end
$upscope $end
$enddefinitions $end
#0
$dumpvars
b0 (
x'
bx &
x%
0$
1#
b11001100 "
0!
$end
#9000
1$
#10000
b0 &
0'
b11001100 (
1!
#11000
0$
#20000
0!
#29000
1$
#30000
b11001100 &
1'
1!
#31000
0$
#40000
0!
#49000
1$
#50000
b0 (
1!
b0 "
#51000
0$
#60000
0!
#69000
1$
#70000
b0 &
0'
1!
#71000
0$
#80000
0!
#89000
1$
#90000
1!
#91000
0$
#100000
0!
b1010101 "
#109000
1$
#110000
b1010101 (
1!
#111000
0$
#120000
0!
#129000
1$
#130000
b1010101 &
1!
#131000
0$
#140000
0!
#149000
1$
#150000
b0 (
1!
b0 "
#151000
0$
#160000
0!
#169000
1$
#170000
b0 &
1!
#171000
0$
#180000
0!
#189000
1$
#190000
1!
#191000
0$
#200000
0!
1%
b1010101 "
0#
#209000
1$
#210000
b1 (
1!
#211000
0$
#220000
0!
#229000
1$
#230000
b1 &
b11 (
1!
#231000
0$
#240000
0!
#249000
1$
#250000
b11 &
b111 (
1!
#251000
0$
#260000
0!
#269000
1$
#270000
b111 &
b1111 (
1!
#271000
0$
#280000
0!
#289000
1$
#290000
b1111 &
b11111 (
1!
#291000
0$
#300000
0!
#309000
1$
#310000
b11111 &
b111111 (
1!
#311000
0$
#320000
0!
#329000
1$
#330000
b111111 &
b1111111 (
1!
#331000
0$
#340000
0!
#349000
1$
#350000
b1111111 &
b11111111 (
1!
#351000
0$
#360000
0!
#369000
1$
#370000
b11111111 &
1'
1!
#371000
0$
#380000
0!
#389000
1$
#390000
1!
#391000
0$
#400000
0!
#409000
1$
#410000
1!
#411000
0$
#420000
0!
#429000
1$
#430000
1!
#431000
0$
#440000
0!
#449000
1$
#450000
1!
#451000
0$
#460000
0!
#469000
1$
#470000
1!
#471000
0$
#480000
0!
#489000
1$
#490000
1!
#491000
0$
#500000
0!
#509000
1$
#510000
1!
#511000
0$
#520000
0!
#529000
1$
#530000
1!
#531000
0$
#540000
0!
#549000
1$
#550000
1!
#551000
0$
#560000
0!
#569000
1$
#570000
1!
#571000
0$
#580000
0!
#589000
1$
#590000
1!
#591000
0$
#600000
0!
#609000
1$
#610000
1!
#611000
0$
#620000
0!
#629000
1$
#630000
1!
#631000
0$
#640000
0!
#649000
1$
#650000
b11111110 (
1!
0%
#651000
0$
#660000
0!
#669000
1$
#670000
b11111110 &
b11111100 (
1!
#671000
0$
#680000
0!
#689000
1$
#690000
b11111100 &
b11111000 (
1!
#691000
0$
#700000
0!
#709000
1$
#710000
b11111000 &
b11110000 (
1!
#711000
0$
#720000
0!
#729000
1$
#730000
b11110000 &
b11100000 (
1!
#731000
0$
#740000
0!
#749000
1$
#750000
b11100000 &
b11000001 (
1!
1%
#751000
0$
#760000
0!
#769000
1$
#770000
b11000001 &
b10000011 (
1!
#771000
0$
#780000
0!
#789000
1$
#790000
b10000011 &
b111 (
1!
#791000
0$
#800000
0!
#809000
1$
#810000
b111 &
0'
b1110 (
1!
0%
#811000
0$
#820000
0!
#829000
1$
#830000
b1110 &
b11100 (
1!
#831000
0$
#840000
0!
#849000
1$
#850000
b11100 &
b111000 (
1!
#851000
0$
#860000
0!
#869000
1$
#870000
b111000 &
b1110000 (
1!
#871000
0$
#880000
0!
#889000
1$
#890000
b1110000 &
b11100001 (
1!
1%
#891000
0$
#900000
0!
#909000
1$
#910000
b11100001 &
1'
b11000011 (
1!
#911000
0$
#915000
b11001100 "
#920000
0!
#929000
1$
#930000
b11000011 &
b10000111 (
1!
#931000
0$
#935000
1#
#940000
b0 "
0!
#949000
1$
#950000
b10000111 &
b0 (
1!
#951000
0$
#960000
0!
#967000
b1010101 "
#969000
1$
#970000
b0 &
0'
b1010101 (
1!
#971000
0$
#980000
0!
#987000
0#
#989000
1$
#990000
b1010101 &
b10101011 (
1!
#991000
0$
#1000000
0!
#1009000
1$
#1010000
b10101011 &
1'
b1010111 (
1!
#1011000
0$
#1020000
0!
#1022000
b0 "
#1029000
1$
#1030000
b1010111 &
0'
b10101111 (
1!
#1031000
0$
#1040000
0!
#1049000
1$
0%
b1010101 "
#1050000
b10101111 &
1'
b1011110 (
1!
#1051000
0$
#1060000
0!
#1069000
1$
