shiftregister.v
//------------------------------------------------------------------------
// Shift Register
//   Parameterized width (in bits)
//   Shift register can operate in two modes:
//      - serial in, parallel out
//      - parallel in, serial out
//------------------------------------------------------------------------

module shiftregister
#(parameter width = 8)
(
input               clk,                // FPGA Clock
input               peripheralClkEdge,  // Edge indicator
input               parallelLoad,       // 1 = Load shift reg with parallelDataIn
input  [width-1:0]  parallelDataIn,     // Load shift reg in parallel
input               serialDataIn,       // Load shift reg serially
output reg[width-1:0]  parallelDataOut,    // Shift reg data contents
output reg           serialDataOut       // Positive edge synchronized
);

    reg [width:0]      shiftregistermem;
    always @(posedge clk) begin
        if( parallelLoad == 1)
          // When parallelLoad is asserted, the shift register will take the value of parallelDataIn.
        parallelDataOut <= parallelDataIn;
        //--
        else if (peripheralClkEdge == 1) begin
          // When the peripheral clock peripheralClkEdge has an edge, the shift register advances one position:
          // serialDataIn is loaded into the LSB (Least Significant Bit), and the rest of the bits shift up by one.
          shiftregistermem <= {parallelDataIn, serialDataIn};
          parallelDataOut <= shiftregistermem[width-1:0];
        end
        serialDataOut <= parallelDataOut[width-1];
        shiftregistermem <= {parallelDataIn, serialDataIn};
    end
endmodule

shiftregister.t.v
//------------------------------------------------------------------------
// Shift Register test bench
//------------------------------------------------------------------------
`timescale 1 ns / 1 ps
`include "shiftregister.v"
module testshiftregister();

    reg             clk;
    reg             peripheralClkEdge;
    reg             parallelLoad;
    wire[7:0]       parallelDataOut;
    wire            serialDataOut;
    reg[7:0]        parallelDataIn;
    reg             serialDataIn;

    // Instantiate with parameter width = 8
    shiftregister #(8) dut(.clk(clk),
    		           .peripheralClkEdge(peripheralClkEdge),
    		           .parallelLoad(parallelLoad),
    		           .parallelDataIn(parallelDataIn),
    		           .serialDataIn(serialDataIn),
    		           .parallelDataOut(parallelDataOut),
    		           .serialDataOut(serialDataOut));
    // Generate clock (50MHz)
    initial clk=0;
    initial peripheralClkEdge = 0;
    always #10 clk=!clk;    // 50MHz Clock

    always
      begin
      peripheralClkEdge <= 1'b0;
      #9;
      peripheralClkEdge <= 1'b1;
      #2;
      peripheralClkEdge <= 1'b0;
      #9;
      end

    initial begin
    $dumpfile("shifter.vcd");
    $dumpvars(0, dut);

    //Hey Emma! I think the reason that serial stuff doesnt work is because we arent setting peripheral clock edge to anything. I think this clock edge comes from the
    //input conditioner "rising" variable. But I am not entirely sure what input we need to condition? I think its a button press on the FPGA but for this test, just a  random
    // on off signal ?  I think so. Lets chat

    //Case 1: PIPO
    //Parallel load is always asserted, 8 bits are loaded into place. After these 8 bits are loaded, parallel data in goes to zero, and we observe a full shift in the output.
    parallelDataIn = 8'b11001100;
    parallelLoad= 1;
    serialDataIn = 0;
    #20;
    $display("current register   %b", parallelDataOut);
    parallelDataIn = 8'b0000000;
    #20;
    $display("current register   %b", parallelDataOut);
    parallelDataIn = 8'b1010101;
    #20;
    $display("current register   %b", parallelDataOut);



    //Case 2: SIS0
    //Parallel load is never asserted, we observe a reading of serial data into the LSB
    parallelLoad = 0;
    serialDataIn = 1;
    #5
    parallelDataIn = 8'b0110000;
    #15;
    // not working as expected // GTKWAVE does not register serial dataout as getting anything written to it. we should look at shift register.v
    $display("current register LSB   %b", parallelDataOut);
    serialDataIn = 0;
    //parallelDataIn = 8'b0010100;
    #20;
    $display("current register LSB   %b", serialDataOut);
    serialDataIn = 1;
    //parallelDataIn = 8'b1000101;
    #20;
    $display("current register LSB   %b", serialDataOut);

    //Case 3:
    //Peripheral clock edge is non-periodic, so we observe non-periodic shifting. Parallel load is always asserted.

    //Case 4:
    //Parallel load is toggled.

    parallelDataIn = 8'b11001100; #20
    parallelLoad= 1;
    serialDataIn = 1;
    #5;
    $display("current register   %b", parallelDataOut);
    parallelDataIn = 8'b0000000;
    serialDataIn = 1;
    #27;
    $display("current register   %b", parallelDataOut);
    parallelDataIn = 8'b1010101;
    serialDataIn = 1;
    #20;
    $display("current register   %b", parallelDataOut);

    parallelLoad= 0;
    #35;
    $display("current register   %b", parallelDataOut);
    serialDataIn = 1;
    parallelDataIn = 8'b0000000;
    #27;
    $display("current register   %b", parallelDataOut);
    parallelDataIn = 8'b1010101;
    serialDataIn = 0;
    #20;
    $display("current register   %b", parallelDataOut);
    $dumpflush;
    $finish;
    end

endmodule

shifter.vcd
$date
	Thu Oct 11 13:03:56 2018
$end
$version
	Icarus Verilog
$end
$timescale
	1ps
$end
$scope module testshiftregister $end
$scope module dut $end
$var wire 1 ! clk $end
$var wire 8 " parallelDataIn [7:0] $end
$var wire 1 # parallelLoad $end
$var wire 1 $ peripheralClkEdge $end
$var wire 1 % serialDataIn $end
$var reg 8 & parallelDataOut [7:0] $end
$var reg 1 ' serialDataOut $end
$var reg 9 ( shiftregistermem [8:0] $end
$upscope $end
$upscope $end
$enddefinitions $end
#0
$dumpvars
bx (
x'
bx &
0%
0$
1#
b11001100 "
0!
$end
#9000
1$
#10000
b110011000 (
b11001100 &
1!
#11000
0$
#20000
0!
b0 "
#29000
1$
#30000
b0 (
1'
b0 &
1!
#31000
0$
#40000
0!
b1010101 "
#49000
1$
#50000
b10101010 (
0'
b1010101 &
1!
#51000
0$
#60000
0!
1%
0#
#65000
b110000 "
#69000
1$
#70000
b10101010 &
b1100001 (
1!
#71000
0$
#80000
0!
0%
#89000
1$
#90000
1'
b1100001 &
b1100000 (
1!
#91000
0$
#100000
0!
1%
#109000
1$
#110000
0'
b1100000 &
b1100001 (
1!
#111000
0$
#120000
0!
b11001100 "
#129000
1$
#130000
b1100001 &
b110011001 (
1!
#131000
0$
#140000
0!
1#
#145000
b0 "
#149000
1$
#150000
b1 (
b0 &
1!
#151000
0$
#160000
0!
#169000
1$
#170000
1!
#171000
0$
#172000
b1010101 "
#180000
0!
#189000
1$
#190000
b10101011 (
b1010101 &
1!
#191000
0$
#192000
0#
#200000
0!
#209000
1$
#210000
b10101011 &
1!
#211000
0$
#220000
0!
#227000
b0 "
#229000
1$
#230000
1'
b1 (
1!
#231000
0$
#240000
0!
#249000
1$
#250000
b1 &
1!
#251000
0$
#254000
0%
b1010101 "
#260000
0!
#269000
1$
#270000
0'
b10101010 (
1!
#271000
0$
