shiftregister.v
//------------------------------------------------------------------------
// Shift Register
//   Parameterized width (in bits)
//   Shift register can operate in two modes:
//      - serial in, parallel out
//      - parallel in, serial out
//------------------------------------------------------------------------

module shiftregister
#(parameter width = 8)
(
input               clk,                // FPGA Clock
input               peripheralClkEdge,  // Edge indicator
input               parallelLoad,       // 1 = Load shift reg with parallelDataIn
input  [width-1:0]  parallelDataIn,     // Load shift reg in parallel
input               serialDataIn,       // Load shift reg serially
output reg[width-1:0]  parallelDataOut,    // Shift reg data contents
output reg           serialDataOut       // Positive edge synchronized
);

    reg [width:0]      shiftregistermem;
    always @(posedge clk) begin
        if( parallelLoad == 1)
          // When parallelLoad is asserted, the shift register will take the value of parallelDataIn.

        parallelDataOut <= parallelDataIn;
        //--
        else if (peripheralClkEdge == 1) begin
          // When the peripheral clock peripheralClkEdge has an edge, the shift register advances one position:
          // serialDataIn is loaded into the LSB (Least Significant Bit), and the rest of the bits shift up by one.
          shiftregistermem <= {parallelDataIn, serialDataIn};
          parallelDataOut <= shiftregistermem[width-1:0];
        end
        else
        // only works when parallelLoad is not asserted
        serialDataOut <= parallelDataOut[width-1];
    end
endmodule

shiftregister.t.v
//------------------------------------------------------------------------
// Shift Register test bench
//------------------------------------------------------------------------
`timescale 1 ns / 1 ps
`include "shiftregister.v"
module testshiftregister();

    reg             clk;
    reg             peripheralClkEdge;
    reg             parallelLoad;
    wire[7:0]       parallelDataOut;
    wire            serialDataOut;
    reg[7:0]        parallelDataIn;
    reg             serialDataIn;

    // Instantiate with parameter width = 8
    shiftregister #(8) dut(.clk(clk),
    		           .peripheralClkEdge(peripheralClkEdge),
    		           .parallelLoad(parallelLoad),
    		           .parallelDataIn(parallelDataIn),
    		           .serialDataIn(serialDataIn),
    		           .parallelDataOut(parallelDataOut),
    		           .serialDataOut(serialDataOut));
    // Generate clock (50MHz)
    initial clk=0;
    always #10 clk=!clk;    // 50MHz Clock

    initial begin
    $dumpfile("shifter.vcd");
    $dumpvars(0, dut);


    //Case 1: PIPO
    //Parallel load is always asserted, 8 bits are loaded into place. After these 8 bits are loaded, parallel data in goes to zero, and we observe a full shift in the output.
    parallelDataIn = 8'b11001100;
    parallelLoad= 1;
    #100;
    $display("current register   %b", parallelDataOut);
    parallelDataIn = 8'b0000000;
    #100;
    $display("current register   %b", parallelDataOut);
    parallelDataIn = 8'b1010101;
    #100;
    $display("current register   %b", parallelDataOut);



    //Case 2: SIS0
    //Parallel load is never asserted, we observe a reading of serial data into the LSB
    parallelLoad = 0;
    serialDataIn = 1;
    #100;
    $display("current register LSB   %b", parallelDataOut); // not working as expected
    serialDataIn = 0;
    #100;
    $display("current register LSB   %b", serialDataOut);
    serialDataIn = 1;
    #100;
    $display("current register LSB   %b", serialDataOut);

    //Case 3:
    //Peripheral clock edge is non-periodic, so we observe non-periodic shifting. Parallel load is always asserted.

    //Case 4:
    //Parallel load is toggled.

    $dumpflush;
    $finish;
    end

endmodule

shifter.vcd
$date
	Wed Oct 10 01:43:10 2018
$end
$version
	Icarus Verilog
$end
$timescale
	1ps
$end
$scope module testshiftregister $end
$scope module dut $end
$var wire 1 ! clk $end
$var wire 8 " parallelDataIn [7:0] $end
$var wire 1 # parallelLoad $end
$var wire 1 $ peripheralClkEdge $end
$var wire 1 % serialDataIn $end
$var reg 8 & parallelDataOut [7:0] $end
$var reg 1 ' serialDataOut $end
$var reg 9 ( shiftregistermem [8:0] $end
$upscope $end
$upscope $end
$enddefinitions $end
#0
$dumpvars
bx (
x'
bx &
x%
x$
1#
b11001100 "
0!
$end
#10000
b11001100 &
1!
#20000
0!
#30000
1!
#40000
0!
#50000
1!
#60000
0!
#70000
1!
#80000
0!
#90000
1!
#100000
0!
b0 "
#110000
b0 &
1!
#120000
0!
#130000
1!
#140000
0!
#150000
1!
#160000
0!
#170000
1!
#180000
0!
#190000
1!
#200000
0!
b1010101 "
#210000
b1010101 &
1!
#220000
0!
#230000
1!
#240000
0!
#250000
1!
#260000
0!
#270000
1!
#280000
0!
#290000
1!
#300000
0!
1%
0#
#310000
0'
1!
#320000
0!
#330000
1!
#340000
0!
#350000
1!
#360000
0!
#370000
1!
#380000
0!
#390000
1!
#400000
0!
0%
#410000
1!
#420000
0!
#430000
1!
#440000
0!
#450000
1!
#460000
0!
#470000
1!
#480000
0!
#490000
1!
#500000
0!
1%
