shiftregister.v
//------------------------------------------------------------------------
// Shift Register
//   Parameterized width (in bits)
//   Shift register can operate in two modes:
//      - serial in, parallel out
//      - parallel in, serial out
//------------------------------------------------------------------------

module shiftregister
#(parameter width = 8)
(
input               clk,                // FPGA Clock
input               peripheralClkEdge,  // Edge indicator
input               parallelLoad,       // 1 = Load shift reg with parallelDataIn
input  [width-1:0]  parallelDataIn,     // Load shift reg in parallel
input               serialDataIn,       // Load shift reg serially
output reg[width-1:0]  parallelDataOut,    // Shift reg data contents
output reg           serialDataOut       // Positive edge synchronized
);

    reg [width-1:0]      shiftregistermem;
    //assign parallelDataOut = shiftregistermem;
    initial shiftregistermem = 0;

    always @(posedge clk) begin
        if( parallelLoad == 1)
          // When parallelLoad is asserted, the shift register will take the value of parallelDataIn.
            shiftregistermem <= parallelDataIn;
        //--
        else if (peripheralClkEdge == 1) begin
          // When the peripheral clock peripheralClkEdge has an edge, the shift register advances one position:
          // serialDataIn is loaded into the LSB (Least Significant Bit), and the rest of the bits shift up by one.
          shiftregistermem <= {shiftregistermem[width-2:0], serialDataIn};
          //parallelDataOut <= shiftregistermem[width-1:0];
          //hiftregistermem <= parallelDataOut;
        end
        serialDataOut <= shiftregistermem[width-1];
        parallelDataOut <= shiftregistermem;
        //shiftregistermem <= parallelDataOut;
    end

/*
    always @(posedge clk) begin
        if( parallelLoad == 1)
          // When parallelLoad is asserted, the shift register will take the value of parallelDataIn.
        parallelDataOut <= parallelDataIn;
        //--
        else if (peripheralClkEdge == 1) begin
          // When the peripheral clock peripheralClkEdge has an edge, the shift register advances one position:
          // serialDataIn is loaded into the LSB (Least Significant Bit), and the rest of the bits shift up by one.
          shiftregistermem <= {parallelDataIn, serialDataIn};
          parallelDataOut <= shiftregistermem[width-1:0];
          shiftregistermem <= parallelDataOut;
        end
        serialDataOut <= parallelDataOut[width-1];
        shiftregistermem <= {parallelDataIn, serialDataIn};
    end
  */
endmodule

shiftregister.t.v
//------------------------------------------------------------------------
// Shift Register test bench
//------------------------------------------------------------------------
`timescale 1 ns / 1 ps
`include "shiftregister.v"
module testshiftregister();

    reg             clk;
    reg             peripheralClkEdge;
    reg             parallelLoad;
    wire[7:0]       parallelDataOut;
    wire            serialDataOut;
    reg[7:0]        parallelDataIn;
    reg             serialDataIn;

    // Instantiate with parameter width = 8
    shiftregister #(8) dut(.clk(clk),
    		           .peripheralClkEdge(peripheralClkEdge),
    		           .parallelLoad(parallelLoad),
    		           .parallelDataIn(parallelDataIn),
    		           .serialDataIn(serialDataIn),
    		           .parallelDataOut(parallelDataOut),
    		           .serialDataOut(serialDataOut));
    // Generate clock (50MHz)
    initial clk=0;
    initial peripheralClkEdge = 0;
    always #10 clk=!clk;    // 50MHz Clock
/*
    always
      begin
      peripheralClkEdge <= 1'b0;
      #9;
      peripheralClkEdge <= 1'b1;
      #2;
      peripheralClkEdge <= 1'b0;
      #9;
      end
*/
    initial begin
    $dumpfile("shifter.vcd");
    $dumpvars(0, dut);

    //Hey Emma! I think the reason that serial stuff doesnt work is because we arent setting peripheral clock edge to anything. I think this clock edge comes from the
    //input conditioner "rising" variable. But I am not entirely sure what input we need to condition? I think its a button press on the FPGA but for this test, just a  random
    // on off signal ?  I think so. Lets chat

    //Case 1: PIPO
    //Parallel load is always asserted, 8 bits are loaded into place. After these 8 bits are loaded, parallel data in goes to zero, and we observe a full shift in the output.
    $display("PIPO");

    parallelLoad = 1;
    parallelDataIn = 8'b11001100;

    #50;
    $display("current register   %b", parallelDataOut);
    parallelDataIn = 8'b0000000;
    #50;
    $display("current register   %b", parallelDataOut);
    parallelDataIn = 8'b1010101;
    #50;
    $display("current register   %b", parallelDataOut);



    //Case 2: SIS0
    //Parallel load is never asserted, we observe a reading of serial data into the LSB

    parallelLoad = 1;
    parallelDataIn = 8'b1010101;
    #50
    // not working as expected // GTKWAVE does not register serial dataout as getting anything written to it. we should look at shift register.v
    $display("Parallel Output Register   %b", parallelDataOut);
    parallelLoad = 0;
    serialDataIn = 0;
    //parallelDataIn = 8'b0010100;
    #20;
    $display("current register LSB   %b", serialDataOut);
    serialDataIn = 1;
    //parallelDataIn = 8'b1000101;
    #50;
    $display("current register LSB   %b", serialDataOut);


    //case 3:
    //Case 2: SIPO
    //Parallel load is never asserted, we observe a reading of serial data into the LSB
    parallelLoad = 1;
    parallelDataIn = 8'b00000000;
    #50
    $display("SIPO   %b", parallelDataOut);
    parallelLoad = 0;
    serialDataIn = 1;
    peripheralClkEdge = 1;
    $display("current register   %b", parallelDataOut);
    #20
    serialDataIn = 1;
    $display("current register   %b", parallelDataOut);
    #50
    serialDataIn = 0;
    $display("current register   %b", parallelDataOut);
    #50
    serialDataIn = 1;
    $display("current register   %b", parallelDataOut);
    #50
    serialDataIn = 1;
    $display("current register   %b", parallelDataOut);
    #50
    serialDataIn = 1;
    $display("current register   %b", parallelDataOut);
    #50
    serialDataIn = 1;
    $display("current register   %b", parallelDataOut);
    #50
    serialDataIn = 1;
    $display("current register   %b", parallelDataOut);
    #50

    $display("next case");

    #15;
    // not working as expected // GTKWAVE does not register serial dataout as getting anything written to it. we should look at shift register.v
    $display("current register   %b", parallelDataOut);
    serialDataIn = 0;
    //parallelDataIn = 8'b0010100;
    #20;
    $display("current register LSB   %b", serialDataOut);
    serialDataIn = 1;
    //parallelDataIn = 8'b1000101;
    #20;
    $display("current register LSB   %b", serialDataOut);
    //Case 3:
    //Peripheral clock edge is non-periodic, so we observe non-periodic shifting. Parallel load is always asserted.

    //Case 4:
    //Parallel load is toggled.

    parallelDataIn = 8'b11001100; #20
    parallelLoad= 1;
    serialDataIn = 1;
    #5;
    $display("current register   %b", parallelDataOut);
    parallelDataIn = 8'b0000000;
    serialDataIn = 1;
    #27;
    $display("current register   %b", parallelDataOut);
    parallelDataIn = 8'b1010101;
    serialDataIn = 1;
    #20;
    $display("current register   %b", parallelDataOut);

    parallelLoad= 0;
    #35;
    $display("current register   %b", parallelDataOut);
    serialDataIn = 1;
    parallelDataIn = 8'b0000000;
    #27;
    $display("current register   %b", parallelDataOut);
    parallelDataIn = 8'b1010101;
    serialDataIn = 0;
    #20;
    $display("current register   %b", parallelDataOut);
    $dumpflush;
    $finish;
    end

endmodule

shifter.vcd
$date
	Thu Oct 11 21:26:25 2018
$end
$version
	Icarus Verilog
$end
$timescale
	1ps
$end
$scope module testshiftregister $end
$scope module dut $end
$var wire 1 ! clk $end
$var wire 8 " parallelDataIn [7:0] $end
$var wire 1 # parallelLoad $end
$var wire 1 $ peripheralClkEdge $end
$var wire 1 % serialDataIn $end
$var reg 8 & parallelDataOut [7:0] $end
$var reg 1 ' serialDataOut $end
$var reg 8 ( shiftregistermem [7:0] $end
$upscope $end
$upscope $end
$enddefinitions $end
#0
$dumpvars
b0 (
x'
bx &
x%
0$
1#
b11001100 "
0!
$end
#10000
b0 &
0'
b11001100 (
1!
#20000
0!
#30000
b11001100 &
1'
1!
#40000
0!
#50000
b0 (
1!
b0 "
#60000
0!
#70000
b0 &
0'
1!
#80000
0!
#90000
1!
#100000
0!
b1010101 "
#110000
b1010101 (
1!
#120000
0!
#130000
b1010101 &
1!
#140000
0!
#150000
1!
#160000
0!
#170000
1!
#180000
0!
#190000
1!
#200000
0!
0%
0#
#210000
1!
#220000
0!
1%
#230000
1!
#240000
0!
#250000
1!
#260000
0!
#270000
b0 (
1!
b0 "
1#
#280000
0!
#290000
b0 &
1!
#300000
0!
#310000
1!
#320000
0!
1$
0#
#330000
b1 (
1!
#340000
0!
#350000
b1 &
b11 (
1!
#360000
0!
#370000
b11 &
b111 (
1!
#380000
0!
#390000
b111 &
b1110 (
1!
0%
#400000
0!
#410000
b1110 &
b11100 (
1!
#420000
0!
#430000
b11100 &
b111000 (
1!
#440000
0!
1%
#450000
b111000 &
b1110001 (
1!
#460000
0!
#470000
b1110001 &
b11100011 (
1!
#480000
0!
#490000
b11100011 &
1'
b11000111 (
1!
#500000
0!
#510000
b11000111 &
b10001111 (
1!
#520000
0!
#530000
b10001111 &
b11111 (
1!
#540000
0!
#550000
b11111 &
0'
b111111 (
1!
#560000
0!
#570000
b111111 &
b1111111 (
1!
#580000
0!
#590000
b1111111 &
b11111111 (
1!
#600000
0!
#610000
b11111111 &
1'
1!
#620000
0!
#630000
1!
#640000
0!
#650000
1!
#660000
0!
#670000
1!
#680000
0!
#690000
1!
#700000
0!
#705000
0%
#710000
b11111110 (
1!
#720000
0!
#725000
1%
#730000
b11111110 &
b11111101 (
1!
#740000
0!
#745000
b11001100 "
#750000
b11111101 &
b11111011 (
1!
#760000
0!
#765000
1#
#770000
b11111011 &
b0 (
b0 "
1!
#780000
0!
#790000
b0 &
0'
1!
#797000
b1010101 "
#800000
0!
#810000
b1010101 (
1!
#817000
0#
#820000
0!
#830000
b1010101 &
b10101011 (
1!
#840000
0!
#850000
b10101011 &
1'
b1010111 (
1!
#852000
b0 "
#860000
0!
#870000
b1010111 &
0'
b10101111 (
1!
#879000
0%
b1010101 "
#880000
0!
#890000
b10101111 &
1'
b1011110 (
1!
