testing_research/pwm.v
module pwm #(parameter CTR_LEN = 8) (
    input clk,
    input rst,
    input [CTR_LEN - 1 : 0] compare,
    output pwm
  );
 
  reg pwm_d, pwm_q;
  reg [CTR_LEN - 1: 0] ctr_d, ctr_q;
 
  assign pwm = pwm_q;
 
  always @(*) begin
    ctr_d = ctr_q + 1'b1;
 
    if (compare > ctr_q)
    pwm_d = 1'b1;
    else
    pwm_d = 1'b0;
  end
 
  always @(posedge clk) begin
    if (rst) begin
      ctr_q <= 1'b0;
    end else begin
      ctr_q <= ctr_d;
    end
 
    pwm_q <= pwm_d;
  end
 
endmodule

testing_research/pwm.t.v
`include "pwm.v"
module pwm_tb ();
 
  reg clk, rst;
  reg [7:0] compare;
  wire pwm;
 
  pwm #(.CTR_LEN(8)) DUT (
    .clk(clk),
    .rst(rst),
    .compare(compare),
    .pwm(pwm)
  );
 
  initial begin
    clk = 1'b0;
    rst = 1'b1;
    repeat(4) #10 clk = ~clk;
    rst = 1'b0;
    forever #10 clk = ~clk; // generate a clock
  end
 
  initial begin
    	$dumpfile("pwm.vcd");
    	$dumpvars(0,DUT);
    compare = 8'd0; // initial value
    @(negedge rst); // wait for reset
    compare = 8'd128;
    repeat(256) @(posedge clk);
    compare = 8'd30;
    repeat(256) @(posedge clk);
    $finish;
  end
 
endmodule

testing_research/pwm.vcd
$date
	Mon Oct  8 14:40:00 2018
$end
$version
	Icarus Verilog
$end
$timescale
	1s
$end
$scope module pwm_tb $end
$scope module DUT $end
$var wire 1 ! clk $end
$var wire 8 " compare [7:0] $end
$var wire 1 # pwm $end
$var wire 1 $ rst $end
$var reg 8 % ctr_d [7:0] $end
$var reg 8 & ctr_q [7:0] $end
$var reg 1 ' pwm_d $end
$var reg 1 ( pwm_q $end
$upscope $end
$upscope $end
$enddefinitions $end
#0
$dumpvars
x(
0'
bx &
bx %
1$
x#
b0 "
0!
$end
#10
b1 %
0#
0(
b0 &
1!
#20
0!
#30
1!
#40
1'
b10000000 "
0$
0!
#50
b10 %
1#
1(
b1 &
1!
#60
0!
#70
b11 %
b10 &
1!
#80
0!
#90
b100 %
b11 &
1!
#100
0!
#110
b101 %
b100 &
1!
#120
0!
#130
b110 %
b101 &
1!
#140
0!
#150
b111 %
b110 &
1!
#160
0!
#170
b1000 %
b111 &
1!
#180
0!
#190
b1001 %
b1000 &
1!
#200
0!
#210
b1010 %
b1001 &
1!
#220
0!
#230
b1011 %
b1010 &
1!
#240
0!
#250
b1100 %
b1011 &
1!
#260
0!
#270
b1101 %
b1100 &
1!
#280
0!
#290
b1110 %
b1101 &
1!
#300
0!
#310
b1111 %
b1110 &
1!
#320
0!
#330
b10000 %
b1111 &
1!
#340
0!
#350
b10001 %
b10000 &
1!
#360
0!
#370
b10010 %
b10001 &
1!
#380
0!
#390
b10011 %
b10010 &
1!
#400
0!
#410
b10100 %
b10011 &
1!
#420
0!
#430
b10101 %
b10100 &
1!
#440
0!
#450
b10110 %
b10101 &
1!
#460
0!
#470
b10111 %
b10110 &
1!
#480
0!
#490
b11000 %
b10111 &
1!
#500
0!
#510
b11001 %
b11000 &
1!
#520
0!
#530
b11010 %
b11001 &
1!
#540
0!
#550
b11011 %
b11010 &
1!
#560
0!
#570
b11100 %
b11011 &
1!
#580
0!
#590
b11101 %
b11100 &
1!
#600
0!
#610
b11110 %
b11101 &
1!
#620
0!
#630
b11111 %
b11110 &
1!
#640
0!
#650
b100000 %
b11111 &
1!
#660
0!
#670
b100001 %
b100000 &
1!
#680
0!
#690
b100010 %
b100001 &
1!
#700
0!
#710
b100011 %
b100010 &
1!
#720
0!
#730
b100100 %
b100011 &
1!
#740
0!
#750
b100101 %
b100100 &
1!
#760
0!
#770
b100110 %
b100101 &
1!
#780
0!
#790
b100111 %
b100110 &
1!
#800
0!
#810
b101000 %
b100111 &
1!
#820
0!
#830
b101001 %
b101000 &
1!
#840
0!
#850
b101010 %
b101001 &
1!
#860
0!
#870
b101011 %
b101010 &
1!
#880
0!
#890
b101100 %
b101011 &
1!
#900
0!
#910
b101101 %
b101100 &
1!
#920
0!
#930
b101110 %
b101101 &
1!
#940
0!
#950
b101111 %
b101110 &
1!
#960
0!
#970
b110000 %
b101111 &
1!
#980
0!
#990
b110001 %
b110000 &
1!
#1000
0!
#1010
b110010 %
b110001 &
1!
#1020
0!
#1030
b110011 %
b110010 &
1!
#1040
0!
#1050
b110100 %
b110011 &
1!
#1060
0!
#1070
b110101 %
b110100 &
1!
#1080
0!
#1090
b110110 %
b110101 &
1!
#1100
0!
#1110
b110111 %
b110110 &
1!
#1120
0!
#1130
b111000 %
b110111 &
1!
#1140
0!
#1150
b111001 %
b111000 &
1!
#1160
0!
#1170
b111010 %
b111001 &
1!
#1180
0!
#1190
b111011 %
b111010 &
1!
#1200
0!
#1210
b111100 %
b111011 &
1!
#1220
0!
#1230
b111101 %
b111100 &
1!
#1240
0!
#1250
b111110 %
b111101 &
1!
#1260
0!
#1270
b111111 %
b111110 &
1!
#1280
0!
#1290
b1000000 %
b111111 &
1!
#1300
0!
#1310
b1000001 %
b1000000 &
1!
#1320
0!
#1330
b1000010 %
b1000001 &
1!
#1340
0!
#1350
b1000011 %
b1000010 &
1!
#1360
0!
#1370
b1000100 %
b1000011 &
1!
#1380
0!
#1390
b1000101 %
b1000100 &
1!
#1400
0!
#1410
b1000110 %
b1000101 &
1!
#1420
0!
#1430
b1000111 %
b1000110 &
1!
#1440
0!
#1450
b1001000 %
b1000111 &
1!
#1460
0!
#1470
b1001001 %
b1001000 &
1!
#1480
0!
#1490
b1001010 %
b1001001 &
1!
#1500
0!
#1510
b1001011 %
b1001010 &
1!
#1520
0!
#1530
b1001100 %
b1001011 &
1!
#1540
0!
#1550
b1001101 %
b1001100 &
1!
#1560
0!
#1570
b1001110 %
b1001101 &
1!
#1580
0!
#1590
b1001111 %
b1001110 &
1!
#1600
0!
#1610
b1010000 %
b1001111 &
1!
#1620
0!
#1630
b1010001 %
b1010000 &
1!
#1640
0!
#1650
b1010010 %
b1010001 &
1!
#1660
0!
#1670
b1010011 %
b1010010 &
1!
#1680
0!
#1690
b1010100 %
b1010011 &
1!
#1700
0!
#1710
b1010101 %
b1010100 &
1!
#1720
0!
#1730
b1010110 %
b1010101 &
1!
#1740
0!
#1750
b1010111 %
b1010110 &
1!
#1760
0!
#1770
b1011000 %
b1010111 &
1!
#1780
0!
#1790
b1011001 %
b1011000 &
1!
#1800
0!
#1810
b1011010 %
b1011001 &
1!
#1820
0!
#1830
b1011011 %
b1011010 &
1!
#1840
0!
#1850
b1011100 %
b1011011 &
1!
#1860
0!
#1870
b1011101 %
b1011100 &
1!
#1880
0!
#1890
b1011110 %
b1011101 &
1!
#1900
0!
#1910
b1011111 %
b1011110 &
1!
#1920
0!
#1930
b1100000 %
b1011111 &
1!
#1940
0!
#1950
b1100001 %
b1100000 &
1!
#1960
0!
#1970
b1100010 %
b1100001 &
1!
#1980
0!
#1990
b1100011 %
b1100010 &
1!
#2000
0!
#2010
b1100100 %
b1100011 &
1!
#2020
0!
#2030
b1100101 %
b1100100 &
1!
#2040
0!
#2050
b1100110 %
b1100101 &
1!
#2060
0!
#2070
b1100111 %
b1100110 &
1!
#2080
0!
#2090
b1101000 %
b1100111 &
1!
#2100
0!
#2110
b1101001 %
b1101000 &
1!
#2120
0!
#2130
b1101010 %
b1101001 &
1!
#2140
0!
#2150
b1101011 %
b1101010 &
1!
#2160
0!
#2170
b1101100 %
b1101011 &
1!
#2180
0!
#2190
b1101101 %
b1101100 &
1!
#2200
0!
#2210
b1101110 %
b1101101 &
1!
#2220
0!
#2230
b1101111 %
b1101110 &
1!
#2240
0!
#2250
b1110000 %
b1101111 &
1!
#2260
0!
#2270
b1110001 %
b1110000 &
1!
#2280
0!
#2290
b1110010 %
b1110001 &
1!
#2300
0!
#2310
b1110011 %
b1110010 &
1!
#2320
0!
#2330
b1110100 %
b1110011 &
1!
#2340
0!
#2350
b1110101 %
b1110100 &
1!
#2360
0!
#2370
b1110110 %
b1110101 &
1!
#2380
0!
#2390
b1110111 %
b1110110 &
1!
#2400
0!
#2410
b1111000 %
b1110111 &
1!
#2420
0!
#2430
b1111001 %
b1111000 &
1!
#2440
0!
#2450
b1111010 %
b1111001 &
1!
#2460
0!
#2470
b1111011 %
b1111010 &
1!
#2480
0!
#2490
b1111100 %
b1111011 &
1!
#2500
0!
#2510
b1111101 %
b1111100 &
1!
#2520
0!
#2530
b1111110 %
b1111101 &
1!
#2540
0!
#2550
b1111111 %
b1111110 &
1!
#2560
0!
#2570
b10000000 %
b1111111 &
1!
#2580
0!
#2590
0'
b10000001 %
b10000000 &
1!
#2600
0!
#2610
b10000010 %
0#
0(
b10000001 &
1!
#2620
0!
#2630
b10000011 %
b10000010 &
1!
#2640
0!
#2650
b10000100 %
b10000011 &
1!
#2660
0!
#2670
b10000101 %
b10000100 &
1!
#2680
0!
#2690
b10000110 %
b10000101 &
1!
#2700
0!
#2710
b10000111 %
b10000110 &
1!
#2720
0!
#2730
b10001000 %
b10000111 &
1!
#2740
0!
#2750
b10001001 %
b10001000 &
1!
#2760
0!
#2770
b10001010 %
b10001001 &
1!
#2780
0!
#2790
b10001011 %
b10001010 &
1!
#2800
0!
#2810
b10001100 %
b10001011 &
1!
#2820
0!
#2830
b10001101 %
b10001100 &
1!
#2840
0!
#2850
b10001110 %
b10001101 &
1!
#2860
0!
#2870
b10001111 %
b10001110 &
1!
#2880
0!
#2890
b10010000 %
b10001111 &
1!
#2900
0!
#2910
b10010001 %
b10010000 &
1!
#2920
0!
#2930
b10010010 %
b10010001 &
1!
#2940
0!
#2950
b10010011 %
b10010010 &
1!
#2960
0!
#2970
b10010100 %
b10010011 &
1!
#2980
0!
#2990
b10010101 %
b10010100 &
1!
#3000
0!
#3010
b10010110 %
b10010101 &
1!
#3020
0!
#3030
b10010111 %
b10010110 &
1!
#3040
0!
#3050
b10011000 %
b10010111 &
1!
#3060
0!
#3070
b10011001 %
b10011000 &
1!
#3080
0!
#3090
b10011010 %
b10011001 &
1!
#3100
0!
#3110
b10011011 %
b10011010 &
1!
#3120
0!
#3130
b10011100 %
b10011011 &
1!
#3140
0!
#3150
b10011101 %
b10011100 &
1!
#3160
0!
#3170
b10011110 %
b10011101 &
1!
#3180
0!
#3190
b10011111 %
b10011110 &
1!
#3200
0!
#3210
b10100000 %
b10011111 &
1!
#3220
0!
#3230
b10100001 %
b10100000 &
1!
#3240
0!
#3250
b10100010 %
b10100001 &
1!
#3260
0!
#3270
b10100011 %
b10100010 &
1!
#3280
0!
#3290
b10100100 %
b10100011 &
1!
#3300
0!
#3310
b10100101 %
b10100100 &
1!
#3320
0!
#3330
b10100110 %
b10100101 &
1!
#3340
0!
#3350
b10100111 %
b10100110 &
1!
#3360
0!
#3370
b10101000 %
b10100111 &
1!
#3380
0!
#3390
b10101001 %
b10101000 &
1!
#3400
0!
#3410
b10101010 %
b10101001 &
1!
#3420
0!
#3430
b10101011 %
b10101010 &
1!
#3440
0!
#3450
b10101100 %
b10101011 &
1!
#3460
0!
#3470
b10101101 %
b10101100 &
1!
#3480
0!
#3490
b10101110 %
b10101101 &
1!
#3500
0!
#3510
b10101111 %
b10101110 &
1!
#3520
0!
#3530
b10110000 %
b10101111 &
1!
#3540
0!
#3550
b10110001 %
b10110000 &
1!
#3560
0!
#3570
b10110010 %
b10110001 &
1!
#3580
0!
#3590
b10110011 %
b10110010 &
1!
#3600
0!
#3610
b10110100 %
b10110011 &
1!
#3620
0!
#3630
b10110101 %
b10110100 &
1!
#3640
0!
#3650
b10110110 %
b10110101 &
1!
#3660
0!
#3670
b10110111 %
b10110110 &
1!
#3680
0!
#3690
b10111000 %
b10110111 &
1!
#3700
0!
#3710
b10111001 %
b10111000 &
1!
#3720
0!
#3730
b10111010 %
b10111001 &
1!
#3740
0!
#3750
b10111011 %
b10111010 &
1!
#3760
0!
#3770
b10111100 %
b10111011 &
1!
#3780
0!
#3790
b10111101 %
b10111100 &
1!
#3800
0!
#3810
b10111110 %
b10111101 &
1!
#3820
0!
#3830
b10111111 %
b10111110 &
1!
#3840
0!
#3850
b11000000 %
b10111111 &
1!
#3860
0!
#3870
b11000001 %
b11000000 &
1!
#3880
0!
#3890
b11000010 %
b11000001 &
1!
#3900
0!
#3910
b11000011 %
b11000010 &
1!
#3920
0!
#3930
b11000100 %
b11000011 &
1!
#3940
0!
#3950
b11000101 %
b11000100 &
1!
#3960
0!
#3970
b11000110 %
b11000101 &
1!
#3980
0!
#3990
b11000111 %
b11000110 &
1!
#4000
0!
#4010
b11001000 %
b11000111 &
1!
#4020
0!
#4030
b11001001 %
b11001000 &
1!
#4040
0!
#4050
b11001010 %
b11001001 &
1!
#4060
0!
#4070
b11001011 %
b11001010 &
1!
#4080
0!
#4090
b11001100 %
b11001011 &
1!
#4100
0!
#4110
b11001101 %
b11001100 &
1!
#4120
0!
#4130
b11001110 %
b11001101 &
1!
#4140
0!
#4150
b11001111 %
b11001110 &
1!
#4160
0!
#4170
b11010000 %
b11001111 &
1!
#4180
0!
#4190
b11010001 %
b11010000 &
1!
#4200
0!
#4210
b11010010 %
b11010001 &
1!
#4220
0!
#4230
b11010011 %
b11010010 &
1!
#4240
0!
#4250
b11010100 %
b11010011 &
1!
#4260
0!
#4270
b11010101 %
b11010100 &
1!
#4280
0!
#4290
b11010110 %
b11010101 &
1!
#4300
0!
#4310
b11010111 %
b11010110 &
1!
#4320
0!
#4330
b11011000 %
b11010111 &
1!
#4340
0!
#4350
b11011001 %
b11011000 &
1!
#4360
0!
#4370
b11011010 %
b11011001 &
1!
#4380
0!
#4390
b11011011 %
b11011010 &
1!
#4400
0!
#4410
b11011100 %
b11011011 &
1!
#4420
0!
#4430
b11011101 %
b11011100 &
1!
#4440
0!
#4450
b11011110 %
b11011101 &
1!
#4460
0!
#4470
b11011111 %
b11011110 &
1!
#4480
0!
#4490
b11100000 %
b11011111 &
1!
#4500
0!
#4510
b11100001 %
b11100000 &
1!
#4520
0!
#4530
b11100010 %
b11100001 &
1!
#4540
0!
#4550
b11100011 %
b11100010 &
1!
#4560
0!
#4570
b11100100 %
b11100011 &
1!
#4580
0!
#4590
b11100101 %
b11100100 &
1!
#4600
0!
#4610
b11100110 %
b11100101 &
1!
#4620
0!
#4630
b11100111 %
b11100110 &
1!
#4640
0!
#4650
b11101000 %
b11100111 &
1!
#4660
0!
#4670
b11101001 %
b11101000 &
1!
#4680
0!
#4690
b11101010 %
b11101001 &
1!
#4700
0!
#4710
b11101011 %
b11101010 &
1!
#4720
0!
#4730
b11101100 %
b11101011 &
1!
#4740
0!
#4750
b11101101 %
b11101100 &
1!
#4760
0!
#4770
b11101110 %
b11101101 &
1!
#4780
0!
#4790
b11101111 %
b11101110 &
1!
#4800
0!
#4810
b11110000 %
b11101111 &
1!
#4820
0!
#4830
b11110001 %
b11110000 &
1!
#4840
0!
#4850
b11110010 %
b11110001 &
1!
#4860
0!
#4870
b11110011 %
b11110010 &
1!
#4880
0!
#4890
b11110100 %
b11110011 &
1!
#4900
0!
#4910
b11110101 %
b11110100 &
1!
#4920
0!
#4930
b11110110 %
b11110101 &
1!
#4940
0!
#4950
b11110111 %
b11110110 &
1!
#4960
0!
#4970
b11111000 %
b11110111 &
1!
#4980
0!
#4990
b11111001 %
b11111000 &
1!
#5000
0!
#5010
b11111010 %
b11111001 &
1!
#5020
0!
#5030
b11111011 %
b11111010 &
1!
#5040
0!
#5050
b11111100 %
b11111011 &
1!
#5060
0!
#5070
b11111101 %
b11111100 &
1!
#5080
0!
#5090
b11111110 %
b11111101 &
1!
#5100
0!
#5110
b11111111 %
b11111110 &
1!
#5120
0!
#5130
b0 %
b11111111 &
1!
#5140
0!
#5150
1'
b1 %
b0 &
b11110 "
1!
#5160
0!
#5170
b10 %
1#
1(
b1 &
1!
#5180
0!
#5190
b11 %
b10 &
1!
#5200
0!
#5210
b100 %
b11 &
1!
#5220
0!
#5230
b101 %
b100 &
1!
#5240
0!
#5250
b110 %
b101 &
1!
#5260
0!
#5270
b111 %
b110 &
1!
#5280
0!
#5290
b1000 %
b111 &
1!
#5300
0!
#5310
b1001 %
b1000 &
1!
#5320
0!
#5330
b1010 %
b1001 &
1!
#5340
0!
#5350
b1011 %
b1010 &
1!
#5360
0!
#5370
b1100 %
b1011 &
1!
#5380
0!
#5390
b1101 %
b1100 &
1!
#5400
0!
#5410
b1110 %
b1101 &
1!
#5420
0!
#5430
b1111 %
b1110 &
1!
#5440
0!
#5450
b10000 %
b1111 &
1!
#5460
0!
#5470
b10001 %
b10000 &
1!
#5480
0!
#5490
b10010 %
b10001 &
1!
#5500
0!
#5510
b10011 %
b10010 &
1!
#5520
0!
#5530
b10100 %
b10011 &
1!
#5540
0!
#5550
b10101 %
b10100 &
1!
#5560
0!
#5570
b10110 %
b10101 &
1!
#5580
0!
#5590
b10111 %
b10110 &
1!
#5600
0!
#5610
b11000 %
b10111 &
1!
#5620
0!
#5630
b11001 %
b11000 &
1!
#5640
0!
#5650
b11010 %
b11001 &
1!
#5660
0!
#5670
b11011 %
b11010 &
1!
#5680
0!
#5690
b11100 %
b11011 &
1!
#5700
0!
#5710
b11101 %
b11100 &
1!
#5720
0!
#5730
b11110 %
b11101 &
1!
#5740
0!
#5750
0'
b11111 %
b11110 &
1!
#5760
0!
#5770
b100000 %
0#
0(
b11111 &
1!
#5780
0!
#5790
b100001 %
b100000 &
1!
#5800
0!
#5810
b100010 %
b100001 &
1!
#5820
0!
#5830
b100011 %
b100010 &
1!
#5840
0!
#5850
b100100 %
b100011 &
1!
#5860
0!
#5870
b100101 %
b100100 &
1!
#5880
0!
#5890
b100110 %
b100101 &
1!
#5900
0!
#5910
b100111 %
b100110 &
1!
#5920
0!
#5930
b101000 %
b100111 &
1!
#5940
0!
#5950
b101001 %
b101000 &
1!
#5960
0!
#5970
b101010 %
b101001 &
1!
#5980
0!
#5990
b101011 %
b101010 &
1!
#6000
0!
#6010
b101100 %
b101011 &
1!
#6020
0!
#6030
b101101 %
b101100 &
1!
#6040
0!
#6050
b101110 %
b101101 &
1!
#6060
0!
#6070
b101111 %
b101110 &
1!
#6080
0!
#6090
b110000 %
b101111 &
1!
#6100
0!
#6110
b110001 %
b110000 &
1!
#6120
0!
#6130
b110010 %
b110001 &
1!
#6140
0!
#6150
b110011 %
b110010 &
1!
#6160
0!
#6170
b110100 %
b110011 &
1!
#6180
0!
#6190
b110101 %
b110100 &
1!
#6200
0!
#6210
b110110 %
b110101 &
1!
#6220
0!
#6230
b110111 %
b110110 &
1!
#6240
0!
#6250
b111000 %
b110111 &
1!
#6260
0!
#6270
b111001 %
b111000 &
1!
#6280
0!
#6290
b111010 %
b111001 &
1!
#6300
0!
#6310
b111011 %
b111010 &
1!
#6320
0!
#6330
b111100 %
b111011 &
1!
#6340
0!
#6350
b111101 %
b111100 &
1!
#6360
0!
#6370
b111110 %
b111101 &
1!
#6380
0!
#6390
b111111 %
b111110 &
1!
#6400
0!
#6410
b1000000 %
b111111 &
1!
#6420
0!
#6430
b1000001 %
b1000000 &
1!
#6440
0!
#6450
b1000010 %
b1000001 &
1!
#6460
0!
#6470
b1000011 %
b1000010 &
1!
#6480
0!
#6490
b1000100 %
b1000011 &
1!
#6500
0!
#6510
b1000101 %
b1000100 &
1!
#6520
0!
#6530
b1000110 %
b1000101 &
1!
#6540
0!
#6550
b1000111 %
b1000110 &
1!
#6560
0!
#6570
b1001000 %
b1000111 &
1!
#6580
0!
#6590
b1001001 %
b1001000 &
1!
#6600
0!
#6610
b1001010 %
b1001001 &
1!
#6620
0!
#6630
b1001011 %
b1001010 &
1!
#6640
0!
#6650
b1001100 %
b1001011 &
1!
#6660
0!
#6670
b1001101 %
b1001100 &
1!
#6680
0!
#6690
b1001110 %
b1001101 &
1!
#6700
0!
#6710
b1001111 %
b1001110 &
1!
#6720
0!
#6730
b1010000 %
b1001111 &
1!
#6740
0!
#6750
b1010001 %
b1010000 &
1!
#6760
0!
#6770
b1010010 %
b1010001 &
1!
#6780
0!
#6790
b1010011 %
b1010010 &
1!
#6800
0!
#6810
b1010100 %
b1010011 &
1!
#6820
0!
#6830
b1010101 %
b1010100 &
1!
#6840
0!
#6850
b1010110 %
b1010101 &
1!
#6860
0!
#6870
b1010111 %
b1010110 &
1!
#6880
0!
#6890
b1011000 %
b1010111 &
1!
#6900
0!
#6910
b1011001 %
b1011000 &
1!
#6920
0!
#6930
b1011010 %
b1011001 &
1!
#6940
0!
#6950
b1011011 %
b1011010 &
1!
#6960
0!
#6970
b1011100 %
b1011011 &
1!
#6980
0!
#6990
b1011101 %
b1011100 &
1!
#7000
0!
#7010
b1011110 %
b1011101 &
1!
#7020
0!
#7030
b1011111 %
b1011110 &
1!
#7040
0!
#7050
b1100000 %
b1011111 &
1!
#7060
0!
#7070
b1100001 %
b1100000 &
1!
#7080
0!
#7090
b1100010 %
b1100001 &
1!
#7100
0!
#7110
b1100011 %
b1100010 &
1!
#7120
0!
#7130
b1100100 %
b1100011 &
1!
#7140
0!
#7150
b1100101 %
b1100100 &
1!
#7160
0!
#7170
b1100110 %
b1100101 &
1!
#7180
0!
#7190
b1100111 %
b1100110 &
1!
#7200
0!
#7210
b1101000 %
b1100111 &
1!
#7220
0!
#7230
b1101001 %
b1101000 &
1!
#7240
0!
#7250
b1101010 %
b1101001 &
1!
#7260
0!
#7270
b1101011 %
b1101010 &
1!
#7280
0!
#7290
b1101100 %
b1101011 &
1!
#7300
0!
#7310
b1101101 %
b1101100 &
1!
#7320
0!
#7330
b1101110 %
b1101101 &
1!
#7340
0!
#7350
b1101111 %
b1101110 &
1!
#7360
0!
#7370
b1110000 %
b1101111 &
1!
#7380
0!
#7390
b1110001 %
b1110000 &
1!
#7400
0!
#7410
b1110010 %
b1110001 &
1!
#7420
0!
#7430
b1110011 %
b1110010 &
1!
#7440
0!
#7450
b1110100 %
b1110011 &
1!
#7460
0!
#7470
b1110101 %
b1110100 &
1!
#7480
0!
#7490
b1110110 %
b1110101 &
1!
#7500
0!
#7510
b1110111 %
b1110110 &
1!
#7520
0!
#7530
b1111000 %
b1110111 &
1!
#7540
0!
#7550
b1111001 %
b1111000 &
1!
#7560
0!
#7570
b1111010 %
b1111001 &
1!
#7580
0!
#7590
b1111011 %
b1111010 &
1!
#7600
0!
#7610
b1111100 %
b1111011 &
1!
#7620
0!
#7630
b1111101 %
b1111100 &
1!
#7640
0!
#7650
b1111110 %
b1111101 &
1!
#7660
0!
#7670
b1111111 %
b1111110 &
1!
#7680
0!
#7690
b10000000 %
b1111111 &
1!
#7700
0!
#7710
b10000001 %
b10000000 &
1!
#7720
0!
#7730
b10000010 %
b10000001 &
1!
#7740
0!
#7750
b10000011 %
b10000010 &
1!
#7760
0!
#7770
b10000100 %
b10000011 &
1!
#7780
0!
#7790
b10000101 %
b10000100 &
1!
#7800
0!
#7810
b10000110 %
b10000101 &
1!
#7820
0!
#7830
b10000111 %
b10000110 &
1!
#7840
0!
#7850
b10001000 %
b10000111 &
1!
#7860
0!
#7870
b10001001 %
b10001000 &
1!
#7880
0!
#7890
b10001010 %
b10001001 &
1!
#7900
0!
#7910
b10001011 %
b10001010 &
1!
#7920
0!
#7930
b10001100 %
b10001011 &
1!
#7940
0!
#7950
b10001101 %
b10001100 &
1!
#7960
0!
#7970
b10001110 %
b10001101 &
1!
#7980
0!
#7990
b10001111 %
b10001110 &
1!
#8000
0!
#8010
b10010000 %
b10001111 &
1!
#8020
0!
#8030
b10010001 %
b10010000 &
1!
#8040
0!
#8050
b10010010 %
b10010001 &
1!
#8060
0!
#8070
b10010011 %
b10010010 &
1!
#8080
0!
#8090
b10010100 %
b10010011 &
1!
#8100
0!
#8110
b10010101 %
b10010100 &
1!
#8120
0!
#8130
b10010110 %
b10010101 &
1!
#8140
0!
#8150
b10010111 %
b10010110 &
1!
#8160
0!
#8170
b10011000 %
b10010111 &
1!
#8180
0!
#8190
b10011001 %
b10011000 &
1!
#8200
0!
#8210
b10011010 %
b10011001 &
1!
#8220
0!
#8230
b10011011 %
b10011010 &
1!
#8240
0!
#8250
b10011100 %
b10011011 &
1!
#8260
0!
#8270
b10011101 %
b10011100 &
1!
#8280
0!
#8290
b10011110 %
b10011101 &
1!
#8300
0!
#8310
b10011111 %
b10011110 &
1!
#8320
0!
#8330
b10100000 %
b10011111 &
1!
#8340
0!
#8350
b10100001 %
b10100000 &
1!
#8360
0!
#8370
b10100010 %
b10100001 &
1!
#8380
0!
#8390
b10100011 %
b10100010 &
1!
#8400
0!
#8410
b10100100 %
b10100011 &
1!
#8420
0!
#8430
b10100101 %
b10100100 &
1!
#8440
0!
#8450
b10100110 %
b10100101 &
1!
#8460
0!
#8470
b10100111 %
b10100110 &
1!
#8480
0!
#8490
b10101000 %
b10100111 &
1!
#8500
0!
#8510
b10101001 %
b10101000 &
1!
#8520
0!
#8530
b10101010 %
b10101001 &
1!
#8540
0!
#8550
b10101011 %
b10101010 &
1!
#8560
0!
#8570
b10101100 %
b10101011 &
1!
#8580
0!
#8590
b10101101 %
b10101100 &
1!
#8600
0!
#8610
b10101110 %
b10101101 &
1!
#8620
0!
#8630
b10101111 %
b10101110 &
1!
#8640
0!
#8650
b10110000 %
b10101111 &
1!
#8660
0!
#8670
b10110001 %
b10110000 &
1!
#8680
0!
#8690
b10110010 %
b10110001 &
1!
#8700
0!
#8710
b10110011 %
b10110010 &
1!
#8720
0!
#8730
b10110100 %
b10110011 &
1!
#8740
0!
#8750
b10110101 %
b10110100 &
1!
#8760
0!
#8770
b10110110 %
b10110101 &
1!
#8780
0!
#8790
b10110111 %
b10110110 &
1!
#8800
0!
#8810
b10111000 %
b10110111 &
1!
#8820
0!
#8830
b10111001 %
b10111000 &
1!
#8840
0!
#8850
b10111010 %
b10111001 &
1!
#8860
0!
#8870
b10111011 %
b10111010 &
1!
#8880
0!
#8890
b10111100 %
b10111011 &
1!
#8900
0!
#8910
b10111101 %
b10111100 &
1!
#8920
0!
#8930
b10111110 %
b10111101 &
1!
#8940
0!
#8950
b10111111 %
b10111110 &
1!
#8960
0!
#8970
b11000000 %
b10111111 &
1!
#8980
0!
#8990
b11000001 %
b11000000 &
1!
#9000
0!
#9010
b11000010 %
b11000001 &
1!
#9020
0!
#9030
b11000011 %
b11000010 &
1!
#9040
0!
#9050
b11000100 %
b11000011 &
1!
#9060
0!
#9070
b11000101 %
b11000100 &
1!
#9080
0!
#9090
b11000110 %
b11000101 &
1!
#9100
0!
#9110
b11000111 %
b11000110 &
1!
#9120
0!
#9130
b11001000 %
b11000111 &
1!
#9140
0!
#9150
b11001001 %
b11001000 &
1!
#9160
0!
#9170
b11001010 %
b11001001 &
1!
#9180
0!
#9190
b11001011 %
b11001010 &
1!
#9200
0!
#9210
b11001100 %
b11001011 &
1!
#9220
0!
#9230
b11001101 %
b11001100 &
1!
#9240
0!
#9250
b11001110 %
b11001101 &
1!
#9260
0!
#9270
b11001111 %
b11001110 &
1!
#9280
0!
#9290
b11010000 %
b11001111 &
1!
#9300
0!
#9310
b11010001 %
b11010000 &
1!
#9320
0!
#9330
b11010010 %
b11010001 &
1!
#9340
0!
#9350
b11010011 %
b11010010 &
1!
#9360
0!
#9370
b11010100 %
b11010011 &
1!
#9380
0!
#9390
b11010101 %
b11010100 &
1!
#9400
0!
#9410
b11010110 %
b11010101 &
1!
#9420
0!
#9430
b11010111 %
b11010110 &
1!
#9440
0!
#9450
b11011000 %
b11010111 &
1!
#9460
0!
#9470
b11011001 %
b11011000 &
1!
#9480
0!
#9490
b11011010 %
b11011001 &
1!
#9500
0!
#9510
b11011011 %
b11011010 &
1!
#9520
0!
#9530
b11011100 %
b11011011 &
1!
#9540
0!
#9550
b11011101 %
b11011100 &
1!
#9560
0!
#9570
b11011110 %
b11011101 &
1!
#9580
0!
#9590
b11011111 %
b11011110 &
1!
#9600
0!
#9610
b11100000 %
b11011111 &
1!
#9620
0!
#9630
b11100001 %
b11100000 &
1!
#9640
0!
#9650
b11100010 %
b11100001 &
1!
#9660
0!
#9670
b11100011 %
b11100010 &
1!
#9680
0!
#9690
b11100100 %
b11100011 &
1!
#9700
0!
#9710
b11100101 %
b11100100 &
1!
#9720
0!
#9730
b11100110 %
b11100101 &
1!
#9740
0!
#9750
b11100111 %
b11100110 &
1!
#9760
0!
#9770
b11101000 %
b11100111 &
1!
#9780
0!
#9790
b11101001 %
b11101000 &
1!
#9800
0!
#9810
b11101010 %
b11101001 &
1!
#9820
0!
#9830
b11101011 %
b11101010 &
1!
#9840
0!
#9850
b11101100 %
b11101011 &
1!
#9860
0!
#9870
b11101101 %
b11101100 &
1!
#9880
0!
#9890
b11101110 %
b11101101 &
1!
#9900
0!
#9910
b11101111 %
b11101110 &
1!
#9920
0!
#9930
b11110000 %
b11101111 &
1!
#9940
0!
#9950
b11110001 %
b11110000 &
1!
#9960
0!
#9970
b11110010 %
b11110001 &
1!
#9980
0!
#9990
b11110011 %
b11110010 &
1!
#10000
0!
#10010
b11110100 %
b11110011 &
1!
#10020
0!
#10030
b11110101 %
b11110100 &
1!
#10040
0!
#10050
b11110110 %
b11110101 &
1!
#10060
0!
#10070
b11110111 %
b11110110 &
1!
#10080
0!
#10090
b11111000 %
b11110111 &
1!
#10100
0!
#10110
b11111001 %
b11111000 &
1!
#10120
0!
#10130
b11111010 %
b11111001 &
1!
#10140
0!
#10150
b11111011 %
b11111010 &
1!
#10160
0!
#10170
b11111100 %
b11111011 &
1!
#10180
0!
#10190
b11111101 %
b11111100 &
1!
#10200
0!
#10210
b11111110 %
b11111101 &
1!
#10220
0!
#10230
b11111111 %
b11111110 &
1!
#10240
0!
#10250
b0 %
b11111111 &
1!
#10260
0!
#10270
1'
b1 %
b0 &
1!
